{
"meta":{"test_sets":[],"test_metrics":[],"learn_metrics":[{"best_value":"Min","name":"RMSE"}],"launch_mode":"Train","parameters":"","iteration_count":1000,"learn_sets":["learn"],"name":"experiment"},
"iterations":[
{"learn":[14.61268541],"iteration":0,"passed_time":0.291107937,"remaining_time":290.8168291},
{"learn":[14.23196558],"iteration":1,"passed_time":0.2930502275,"remaining_time":146.2320635},
{"learn":[13.86674177],"iteration":2,"passed_time":0.2950350074,"remaining_time":98.04996745},
{"learn":[13.49946468],"iteration":3,"passed_time":0.2970778531,"remaining_time":73.97238542},
{"learn":[13.16661202],"iteration":4,"passed_time":0.3001320241,"remaining_time":59.7262728},
{"learn":[12.85632158],"iteration":5,"passed_time":0.302662716,"remaining_time":50.14112328},
{"learn":[12.56784336],"iteration":6,"passed_time":0.305516045,"remaining_time":43.33963324},
{"learn":[12.31617801],"iteration":7,"passed_time":0.3075942626,"remaining_time":38.14168856},
{"learn":[12.01509946],"iteration":8,"passed_time":0.3094519105,"remaining_time":34.0740937},
{"learn":[11.71512571],"iteration":9,"passed_time":0.3112996798,"remaining_time":30.8186683},
{"learn":[11.43264457],"iteration":10,"passed_time":0.3131353732,"remaining_time":28.15371674},
{"learn":[11.17973129],"iteration":11,"passed_time":0.3149778713,"remaining_time":25.93317807},
{"learn":[10.93746433],"iteration":12,"passed_time":0.3419695644,"remaining_time":25.96338155},
{"learn":[10.69387075],"iteration":13,"passed_time":0.3652406336,"remaining_time":25.72337605},
{"learn":[10.4615922],"iteration":14,"passed_time":0.3694737421,"remaining_time":24.26210906},
{"learn":[10.2299235],"iteration":15,"passed_time":0.3715504332,"remaining_time":22.85035164},
{"learn":[10.01419731],"iteration":16,"passed_time":0.3736028978,"remaining_time":21.60303815},
{"learn":[9.795856918],"iteration":17,"passed_time":0.3758058025,"remaining_time":20.50229433},
{"learn":[9.60040151],"iteration":18,"passed_time":0.3776943478,"remaining_time":19.50095554},
{"learn":[9.418664989],"iteration":19,"passed_time":0.3795812771,"remaining_time":18.59948258},
{"learn":[9.249278645],"iteration":20,"passed_time":0.3818643273,"remaining_time":17.80215126},
{"learn":[9.090113396],"iteration":21,"passed_time":0.3838788743,"remaining_time":17.06516087},
{"learn":[8.909548708],"iteration":22,"passed_time":0.385781109,"remaining_time":16.38731059},
{"learn":[8.740140208],"iteration":23,"passed_time":0.3876876983,"remaining_time":15.7659664},
{"learn":[8.59377682],"iteration":24,"passed_time":0.3896038473,"remaining_time":15.19455005},
{"learn":[8.453885414],"iteration":25,"passed_time":0.4221923272,"remaining_time":15.8159741},
{"learn":[8.317732234],"iteration":26,"passed_time":0.4246784188,"remaining_time":15.30415191},
{"learn":[8.180896085],"iteration":27,"passed_time":0.4265705811,"remaining_time":14.80809303},
{"learn":[8.053220863],"iteration":28,"passed_time":0.428315882,"remaining_time":14.34119729},
{"learn":[7.924234474],"iteration":29,"passed_time":0.4334303479,"remaining_time":14.01424792},
{"learn":[7.818879511],"iteration":30,"passed_time":0.4363557653,"remaining_time":13.63963666},
{"learn":[7.719346395],"iteration":31,"passed_time":0.438390265,"remaining_time":13.26130552},
{"learn":[7.624163594],"iteration":32,"passed_time":0.4437748615,"remaining_time":13.00394821},
{"learn":[7.524952543],"iteration":33,"passed_time":0.4464406195,"remaining_time":12.68416584},
{"learn":[7.424464745],"iteration":34,"passed_time":0.4483478508,"remaining_time":12.36159074},
{"learn":[7.327482321],"iteration":35,"passed_time":0.4501821202,"remaining_time":12.05487677},
{"learn":[7.238666841],"iteration":36,"passed_time":0.4522319227,"remaining_time":11.77025247},
{"learn":[7.158842395],"iteration":37,"passed_time":0.456671932,"remaining_time":11.56101049},
{"learn":[7.074348246],"iteration":38,"passed_time":0.4595074095,"remaining_time":11.32273386},
{"learn":[6.992269093],"iteration":39,"passed_time":0.4716298,"remaining_time":11.3191152},
{"learn":[6.925219745],"iteration":40,"passed_time":0.4738514489,"remaining_time":11.08350096},
{"learn":[6.86013671],"iteration":41,"passed_time":0.4758279414,"remaining_time":10.85340876},
{"learn":[6.786739622],"iteration":42,"passed_time":0.4776660501,"remaining_time":10.63084674},
{"learn":[6.73057926],"iteration":43,"passed_time":0.4794979867,"remaining_time":10.41818353},
{"learn":[6.666356486],"iteration":44,"passed_time":0.4813026358,"remaining_time":10.21431149},
{"learn":[6.606182832],"iteration":45,"passed_time":0.4830739252,"remaining_time":10.01853315},
{"learn":[6.547854615],"iteration":46,"passed_time":0.4885086786,"remaining_time":9.905292993},
{"learn":[6.49240675],"iteration":47,"passed_time":0.4903446222,"remaining_time":9.72516834},
{"learn":[6.431317261],"iteration":48,"passed_time":0.4923180642,"remaining_time":9.554989369},
{"learn":[6.377586395],"iteration":49,"passed_time":0.4953271797,"remaining_time":9.411216415},
{"learn":[6.327558015],"iteration":50,"passed_time":0.4989879954,"remaining_time":9.285090346},
{"learn":[6.282040317],"iteration":51,"passed_time":0.5066106083,"remaining_time":9.23590109},
{"learn":[6.237655841],"iteration":52,"passed_time":0.5088962346,"remaining_time":9.092919512},
{"learn":[6.192792003],"iteration":53,"passed_time":0.5106383886,"remaining_time":8.945628067},
{"learn":[6.150579347],"iteration":54,"passed_time":0.5125578696,"remaining_time":8.806676123},
{"learn":[6.115693845],"iteration":55,"passed_time":0.515284637,"remaining_time":8.686226739},
{"learn":[6.078780782],"iteration":56,"passed_time":0.5179487516,"remaining_time":8.568871453},
{"learn":[6.045146957],"iteration":57,"passed_time":0.5198149576,"remaining_time":8.442511897},
{"learn":[6.008080327],"iteration":58,"passed_time":0.5216627773,"remaining_time":8.32007921},
{"learn":[5.977575734],"iteration":59,"passed_time":0.5234675671,"remaining_time":8.200991885},
{"learn":[5.948036502],"iteration":60,"passed_time":0.5252260621,"remaining_time":8.085037251},
{"learn":[5.914888282],"iteration":61,"passed_time":0.5270666453,"remaining_time":7.974008279},
{"learn":[5.884957796],"iteration":62,"passed_time":0.5289229405,"remaining_time":7.866679289},
{"learn":[5.849539885],"iteration":63,"passed_time":0.5311669084,"remaining_time":7.768316035},
{"learn":[5.821387627],"iteration":64,"passed_time":0.5381356981,"remaining_time":7.740875042},
{"learn":[5.797012279],"iteration":65,"passed_time":0.5397271278,"remaining_time":7.637956627},
{"learn":[5.768685095],"iteration":66,"passed_time":0.5412572141,"remaining_time":7.537208667},
{"learn":[5.755484587],"iteration":67,"passed_time":0.5420423961,"remaining_time":7.429169311},
{"learn":[5.731887055],"iteration":68,"passed_time":0.5433635767,"remaining_time":7.331470868},
{"learn":[5.707148487],"iteration":69,"passed_time":0.5447202791,"remaining_time":7.236997993},
{"learn":[5.685365039],"iteration":70,"passed_time":0.5461024435,"remaining_time":7.145481267},
{"learn":[5.663541834],"iteration":71,"passed_time":0.5483138063,"remaining_time":7.067155725},
{"learn":[5.638108797],"iteration":72,"passed_time":0.549609931,"remaining_time":6.979293234},
{"learn":[5.619204893],"iteration":73,"passed_time":0.550923356,"remaining_time":6.89398686},
{"learn":[5.598472793],"iteration":74,"passed_time":0.5522426317,"remaining_time":6.810992457},
{"learn":[5.577007075],"iteration":75,"passed_time":0.5535708772,"remaining_time":6.730256454},
{"learn":[5.562637084],"iteration":76,"passed_time":0.5549648768,"remaining_time":6.652371186},
{"learn":[5.54729991],"iteration":77,"passed_time":0.5562494244,"remaining_time":6.575153453},
{"learn":[5.530737623],"iteration":78,"passed_time":0.5575865703,"remaining_time":6.500471281},
{"learn":[5.513704873],"iteration":79,"passed_time":0.5588781701,"remaining_time":6.427098957},
{"learn":[5.501575529],"iteration":80,"passed_time":0.5601686119,"remaining_time":6.355493263},
{"learn":[5.484080734],"iteration":81,"passed_time":0.5616604499,"remaining_time":6.287857232},
{"learn":[5.472178894],"iteration":82,"passed_time":0.5632263455,"remaining_time":6.222633239},
{"learn":[5.458923342],"iteration":83,"passed_time":0.5645188334,"remaining_time":6.155943469},
{"learn":[5.451382371],"iteration":84,"passed_time":0.5654516991,"remaining_time":6.086921232},
{"learn":[5.441410748],"iteration":85,"passed_time":0.5668750649,"remaining_time":6.024695457},
{"learn":[5.434047468],"iteration":86,"passed_time":0.5677692198,"remaining_time":5.958313767},
{"learn":[5.422107497],"iteration":87,"passed_time":0.5690685349,"remaining_time":5.897619362},
{"learn":[5.40731265],"iteration":88,"passed_time":0.5706611398,"remaining_time":5.841261779},
{"learn":[5.396360181],"iteration":89,"passed_time":0.572003986,"remaining_time":5.783595859},
{"learn":[5.383793239],"iteration":90,"passed_time":0.5733440025,"remaining_time":5.727139541},
{"learn":[5.369605034],"iteration":91,"passed_time":0.5746154307,"remaining_time":5.671204468},
{"learn":[5.357467333],"iteration":92,"passed_time":0.5758978722,"remaining_time":5.616552367},
{"learn":[5.341109968],"iteration":93,"passed_time":0.5773894157,"remaining_time":5.565051177},
{"learn":[5.330529276],"iteration":94,"passed_time":0.5787460703,"remaining_time":5.513317828},
{"learn":[5.319862075],"iteration":95,"passed_time":0.5801645294,"remaining_time":5.463215985},
{"learn":[5.313052243],"iteration":96,"passed_time":0.5819667479,"remaining_time":5.417690447},
{"learn":[5.299677207],"iteration":97,"passed_time":0.5833290617,"remaining_time":5.369008302},
{"learn":[5.287546698],"iteration":98,"passed_time":0.5851043647,"remaining_time":5.325040733},
{"learn":[5.279803754],"iteration":99,"passed_time":0.5866393385,"remaining_time":5.279754047},
{"learn":[5.272254612],"iteration":100,"passed_time":0.5880597663,"remaining_time":5.234314158},
{"learn":[5.268813888],"iteration":101,"passed_time":0.5888904582,"remaining_time":5.184545407},
{"learn":[5.258113767],"iteration":102,"passed_time":0.5903160665,"remaining_time":5.14090788},
{"learn":[5.251018576],"iteration":103,"passed_time":0.5925642417,"remaining_time":5.105168852},
{"learn":[5.24171237],"iteration":104,"passed_time":0.5940742735,"remaining_time":5.063775951},
{"learn":[5.233984943],"iteration":105,"passed_time":0.5954606526,"remaining_time":5.022092674},
{"learn":[5.226240449],"iteration":106,"passed_time":0.5968332373,"remaining_time":4.981047485},
{"learn":[5.220541644],"iteration":107,"passed_time":0.5981646806,"remaining_time":4.940397176},
{"learn":[5.211712096],"iteration":108,"passed_time":0.5997224517,"remaining_time":4.90231839},
{"learn":[5.203388597],"iteration":109,"passed_time":0.6018309651,"remaining_time":4.869359627},
{"learn":[5.196026544],"iteration":110,"passed_time":0.6036301641,"remaining_time":4.834479422},
{"learn":[5.188716772],"iteration":111,"passed_time":0.6056162155,"remaining_time":4.801671423},
{"learn":[5.182163132],"iteration":112,"passed_time":0.6075094452,"remaining_time":4.768680335},
{"learn":[5.17764747],"iteration":113,"passed_time":0.6088871142,"remaining_time":4.732227923},
{"learn":[5.170548056],"iteration":114,"passed_time":0.6102453093,"remaining_time":4.696235641},
{"learn":[5.165901827],"iteration":115,"passed_time":0.6113434992,"remaining_time":4.65885908},
{"learn":[5.160333668],"iteration":116,"passed_time":0.6128711314,"remaining_time":4.625343667},
{"learn":[5.148953243],"iteration":117,"passed_time":0.6143101817,"remaining_time":4.591708308},
{"learn":[5.144729126],"iteration":118,"passed_time":0.6160202519,"remaining_time":4.56062052},
{"learn":[5.139939946],"iteration":119,"passed_time":0.6175496313,"remaining_time":4.528697297},
{"learn":[5.132898872],"iteration":120,"passed_time":0.6195577542,"remaining_time":4.500754264},
{"learn":[5.129073077],"iteration":121,"passed_time":0.6216535057,"remaining_time":4.473867033},
{"learn":[5.127123916],"iteration":122,"passed_time":0.6224410218,"remaining_time":4.438055091},
{"learn":[5.121282057],"iteration":123,"passed_time":0.6238327382,"remaining_time":4.407076441},
{"learn":[5.114489821],"iteration":124,"passed_time":0.6253491203,"remaining_time":4.377443842},
{"learn":[5.107777291],"iteration":125,"passed_time":0.6266916986,"remaining_time":4.347051941},
{"learn":[5.103518754],"iteration":126,"passed_time":0.6280733252,"remaining_time":4.317385928},
{"learn":[5.101133351],"iteration":127,"passed_time":0.6295622131,"remaining_time":4.288892577},
{"learn":[5.096462705],"iteration":128,"passed_time":0.6313703558,"remaining_time":4.262973487},
{"learn":[5.08562082],"iteration":129,"passed_time":0.6328490058,"remaining_time":4.23522027},
{"learn":[5.080483682],"iteration":130,"passed_time":0.6354377305,"remaining_time":4.215231968},
{"learn":[5.07437499],"iteration":131,"passed_time":0.6368825847,"remaining_time":4.187985481},
{"learn":[5.070683732],"iteration":132,"passed_time":0.6386107522,"remaining_time":4.162973851},
{"learn":[5.06432037],"iteration":133,"passed_time":0.6400042896,"remaining_time":4.136147125},
{"learn":[5.057436484],"iteration":134,"passed_time":0.6413250536,"remaining_time":4.109230899},
{"learn":[5.053254656],"iteration":135,"passed_time":0.6426469219,"remaining_time":4.082698092},
{"learn":[5.04801663],"iteration":136,"passed_time":0.6440299073,"remaining_time":4.056918321},
{"learn":[5.045680836],"iteration":137,"passed_time":0.6453215689,"remaining_time":4.030921684},
{"learn":[5.041857933],"iteration":138,"passed_time":0.6468141164,"remaining_time":4.00652485},
{"learn":[5.035264888],"iteration":139,"passed_time":0.6489459501,"remaining_time":3.986382265},
{"learn":[5.028771948],"iteration":140,"passed_time":0.6505690762,"remaining_time":3.963396003},
{"learn":[5.024912247],"iteration":141,"passed_time":0.6519365669,"remaining_time":3.939166017},
{"learn":[5.02239068],"iteration":142,"passed_time":0.6533541996,"remaining_time":3.915556287},
{"learn":[5.017110572],"iteration":143,"passed_time":0.6547926027,"remaining_time":3.892378249},
{"learn":[5.010707886],"iteration":144,"passed_time":0.6561343985,"remaining_time":3.868930419},
{"learn":[5.004389868],"iteration":145,"passed_time":0.6575425941,"remaining_time":3.846173804},
{"learn":[4.997628683],"iteration":146,"passed_time":0.6589017227,"remaining_time":3.823422921},
{"learn":[4.991497851],"iteration":147,"passed_time":0.6602788865,"remaining_time":3.801064941},
{"learn":[4.988345253],"iteration":148,"passed_time":0.6623769544,"remaining_time":3.783105961},
{"learn":[4.98460423],"iteration":149,"passed_time":0.6644065295,"remaining_time":3.764970334},
{"learn":[4.982441783],"iteration":150,"passed_time":0.6657922266,"remaining_time":3.743427817},
{"learn":[4.977461771],"iteration":151,"passed_time":0.6671780106,"remaining_time":3.722151006},
{"learn":[4.973601586],"iteration":152,"passed_time":0.6690439858,"remaining_time":3.703792523},
{"learn":[4.968328804],"iteration":153,"passed_time":0.6704793697,"remaining_time":3.683282771},
{"learn":[4.9640736],"iteration":154,"passed_time":0.6717719879,"remaining_time":3.662240837},
{"learn":[4.960865882],"iteration":155,"passed_time":0.6730294566,"remaining_time":3.641261932},
{"learn":[4.957014156],"iteration":156,"passed_time":0.6743622018,"remaining_time":3.620938446},
{"learn":[4.952244852],"iteration":157,"passed_time":0.6761036641,"remaining_time":3.603033451},
{"learn":[4.949695675],"iteration":158,"passed_time":0.6778814138,"remaining_time":3.585523704},
{"learn":[4.946584698],"iteration":159,"passed_time":0.679167891,"remaining_time":3.565631428},
{"learn":[4.940192834],"iteration":160,"passed_time":0.6805191367,"remaining_time":3.546307799},
{"learn":[4.936727994],"iteration":161,"passed_time":0.6818282822,"remaining_time":3.526988275},
{"learn":[4.932342063],"iteration":162,"passed_time":0.6831052762,"remaining_time":3.507724639},
{"learn":[4.925830838],"iteration":163,"passed_time":0.6844051161,"remaining_time":3.488796811},
{"learn":[4.922571773],"iteration":164,"passed_time":0.685668975,"remaining_time":3.46990057},
{"learn":[4.918395814],"iteration":165,"passed_time":0.6870895032,"remaining_time":3.452003889},
{"learn":[4.911142452],"iteration":166,"passed_time":0.6885210286,"remaining_time":3.434359382},
{"learn":[4.908276131],"iteration":167,"passed_time":0.6899838007,"remaining_time":3.417062632},
{"learn":[4.904584645],"iteration":168,"passed_time":0.6918544707,"remaining_time":3.401958965},
{"learn":[4.89795517],"iteration":169,"passed_time":0.6932552446,"remaining_time":3.384716782},
{"learn":[4.895556491],"iteration":170,"passed_time":0.6950100019,"remaining_time":3.369375974},
{"learn":[4.890591233],"iteration":171,"passed_time":0.6962835804,"remaining_time":3.351876771},
{"learn":[4.884629277],"iteration":172,"passed_time":0.6975500849,"remaining_time":3.334531331},
{"learn":[4.880550786],"iteration":173,"passed_time":0.6988163462,"remaining_time":3.317369551},
{"learn":[4.876384842],"iteration":174,"passed_time":0.7000852973,"remaining_time":3.300402116},
{"learn":[4.872638238],"iteration":175,"passed_time":0.7015221161,"remaining_time":3.284398998},
{"learn":[4.869137118],"iteration":176,"passed_time":0.7027951847,"remaining_time":3.267799079},
{"learn":[4.863587157],"iteration":177,"passed_time":0.7042312328,"remaining_time":3.252124008},
{"learn":[4.858028614],"iteration":178,"passed_time":0.7057726612,"remaining_time":3.237091368},
{"learn":[4.853838176],"iteration":179,"passed_time":0.7071279335,"remaining_time":3.221360586},
{"learn":[4.853462329],"iteration":180,"passed_time":0.7078685965,"remaining_time":3.203007627},
{"learn":[4.851573196],"iteration":181,"passed_time":0.7091228001,"remaining_time":3.187156321},
{"learn":[4.848442087],"iteration":182,"passed_time":0.7103876608,"remaining_time":3.171512125},
{"learn":[4.845547104],"iteration":183,"passed_time":0.7116165822,"remaining_time":3.155864843},
{"learn":[4.839868817],"iteration":184,"passed_time":0.7129493196,"remaining_time":3.140830786},
{"learn":[4.836336958],"iteration":185,"passed_time":0.7143604083,"remaining_time":3.126286948},
{"learn":[4.831124789],"iteration":186,"passed_time":0.7156621579,"remaining_time":3.111408205},
{"learn":[4.827407333],"iteration":187,"passed_time":0.716942966,"remaining_time":3.096583449},
{"learn":[4.824088918],"iteration":188,"passed_time":0.7188645496,"remaining_time":3.084651586},
{"learn":[4.820934539],"iteration":189,"passed_time":0.720974686,"remaining_time":3.073628924},
{"learn":[4.816975227],"iteration":190,"passed_time":0.7226800805,"remaining_time":3.060985263},
{"learn":[4.812340486],"iteration":191,"passed_time":0.7242525688,"remaining_time":3.047896227},
{"learn":[4.806402747],"iteration":192,"passed_time":0.7257340104,"remaining_time":3.034545836},
{"learn":[4.801521788],"iteration":193,"passed_time":0.727105774,"remaining_time":3.020862133},
{"learn":[4.797601172],"iteration":194,"passed_time":0.7288425443,"remaining_time":3.008811529},
{"learn":[4.792694629],"iteration":195,"passed_time":0.73027275,"remaining_time":2.995608627},
{"learn":[4.789794613],"iteration":196,"passed_time":0.7319309964,"remaining_time":2.983454772},
{"learn":[4.785367055],"iteration":197,"passed_time":0.7333485623,"remaining_time":2.970432055},
{"learn":[4.780376856],"iteration":198,"passed_time":0.7353261656,"remaining_time":2.959780194},
{"learn":[4.776691261],"iteration":199,"passed_time":0.7366491747,"remaining_time":2.946596699},
{"learn":[4.773470753],"iteration":200,"passed_time":0.7380628017,"remaining_time":2.933891436},
{"learn":[4.77207327],"iteration":201,"passed_time":0.7394577927,"remaining_time":2.921224349},
{"learn":[4.767347177],"iteration":202,"passed_time":0.7410265576,"remaining_time":2.909350573},
{"learn":[4.763983068],"iteration":203,"passed_time":0.7423720942,"remaining_time":2.896706799},
{"learn":[4.761588849],"iteration":204,"passed_time":0.7441483816,"remaining_time":2.885843724},
{"learn":[4.758558086],"iteration":205,"passed_time":0.7466629253,"remaining_time":2.877914382},
{"learn":[4.753678804],"iteration":206,"passed_time":0.7485252124,"remaining_time":2.867538616},
{"learn":[4.746510889],"iteration":207,"passed_time":0.7511843312,"remaining_time":2.8602788},
{"learn":[4.744840601],"iteration":208,"passed_time":0.7525955494,"remaining_time":2.848340094},
{"learn":[4.741702222],"iteration":209,"passed_time":0.7541835902,"remaining_time":2.837166839},
{"learn":[4.739352853],"iteration":210,"passed_time":0.7558145245,"remaining_time":2.826244833},
{"learn":[4.735539287],"iteration":211,"passed_time":0.7571902439,"remaining_time":2.81446185},
{"learn":[4.730726751],"iteration":212,"passed_time":0.7585261647,"remaining_time":2.802629538},
{"learn":[4.726416092],"iteration":213,"passed_time":0.7598423829,"remaining_time":2.790822958},
{"learn":[4.721293082],"iteration":214,"passed_time":0.7611689464,"remaining_time":2.779151735},
{"learn":[4.718443695],"iteration":215,"passed_time":0.7625640825,"remaining_time":2.767825188},
{"learn":[4.711627962],"iteration":216,"passed_time":0.7639812591,"remaining_time":2.756669705},
{"learn":[4.709790764],"iteration":217,"passed_time":0.7655318924,"remaining_time":2.746082293},
{"learn":[4.706913073],"iteration":218,"passed_time":0.7672803649,"remaining_time":2.736282945},
{"learn":[4.703846389],"iteration":219,"passed_time":0.7686830147,"remaining_time":2.725330688},
{"learn":[4.701001135],"iteration":220,"passed_time":0.7699663416,"remaining_time":2.714044254},
{"learn":[4.700380864],"iteration":221,"passed_time":0.7712314082,"remaining_time":2.702783944},
{"learn":[4.695837486],"iteration":222,"passed_time":0.7728234965,"remaining_time":2.692752721},
{"learn":[4.691242996],"iteration":223,"passed_time":0.7743476864,"remaining_time":2.682561628},
{"learn":[4.690284609],"iteration":224,"passed_time":0.7759509435,"remaining_time":2.672719917},
{"learn":[4.68827119],"iteration":225,"passed_time":0.7773699773,"remaining_time":2.662320188},
{"learn":[4.686922425],"iteration":226,"passed_time":0.7790852613,"remaining_time":2.653008401},
{"learn":[4.686085874],"iteration":227,"passed_time":0.7804019661,"remaining_time":2.642413675},
{"learn":[4.683230741],"iteration":228,"passed_time":0.7816743301,"remaining_time":2.631750692},
{"learn":[4.6773487],"iteration":229,"passed_time":0.7829124524,"remaining_time":2.621054732},
{"learn":[4.671462906],"iteration":230,"passed_time":0.784141631,"remaining_time":2.610410884},
{"learn":[4.664799601],"iteration":231,"passed_time":0.7854355872,"remaining_time":2.600062633},
{"learn":[4.660979386],"iteration":232,"passed_time":0.7868424738,"remaining_time":2.590163851},
{"learn":[4.656281279],"iteration":233,"passed_time":0.7882041937,"remaining_time":2.580189796},
{"learn":[4.651997094],"iteration":234,"passed_time":0.7894840148,"remaining_time":2.570022431},
{"learn":[4.650151977],"iteration":235,"passed_time":0.7907360598,"remaining_time":2.559840465},
{"learn":[4.648478046],"iteration":236,"passed_time":0.792033288,"remaining_time":2.549879319},
{"learn":[4.646364602],"iteration":237,"passed_time":0.7936079136,"remaining_time":2.540879118},
{"learn":[4.642635873],"iteration":238,"passed_time":0.7949071601,"remaining_time":2.531064221},
{"learn":[4.640860821],"iteration":239,"passed_time":0.7960971222,"remaining_time":2.52097422},
{"learn":[4.639446822],"iteration":240,"passed_time":0.7972787521,"remaining_time":2.510931838},
{"learn":[4.637120072],"iteration":241,"passed_time":0.7984982537,"remaining_time":2.501081307},
{"learn":[4.633769267],"iteration":242,"passed_time":0.7998224739,"remaining_time":2.491628036},
{"learn":[4.630491517],"iteration":243,"passed_time":0.8010476437,"remaining_time":2.481934503},
{"learn":[4.627813333],"iteration":244,"passed_time":0.802335392,"remaining_time":2.472502943},
{"learn":[4.622496304],"iteration":245,"passed_time":0.8036020677,"remaining_time":2.463073004},
{"learn":[4.618979301],"iteration":246,"passed_time":0.8048307858,"remaining_time":2.453593448},
{"learn":[4.616563458],"iteration":247,"passed_time":0.8062363271,"remaining_time":2.444716605},
{"learn":[4.614759385],"iteration":248,"passed_time":0.8076529285,"remaining_time":2.43593313},
{"learn":[4.61251363],"iteration":249,"passed_time":0.8091240288,"remaining_time":2.427372086},
{"learn":[4.608796693],"iteration":250,"passed_time":0.8104352357,"remaining_time":2.418390404},
{"learn":[4.60847774],"iteration":251,"passed_time":0.8116684005,"remaining_time":2.409237951},
{"learn":[4.605195659],"iteration":252,"passed_time":0.8130061784,"remaining_time":2.400456977},
{"learn":[4.60103766],"iteration":253,"passed_time":0.8145211113,"remaining_time":2.392254917},
{"learn":[4.599325598],"iteration":254,"passed_time":0.8159201059,"remaining_time":2.383766584},
{"learn":[4.597012808],"iteration":255,"passed_time":0.8173340335,"remaining_time":2.375377035},
{"learn":[4.594161533],"iteration":256,"passed_time":0.8187447247,"remaining_time":2.367032414},
{"learn":[4.592197259],"iteration":257,"passed_time":0.8200453231,"remaining_time":2.358424922},
{"learn":[4.58952828],"iteration":258,"passed_time":0.8213869895,"remaining_time":2.349991348},
{"learn":[4.585816572],"iteration":259,"passed_time":0.8227726727,"remaining_time":2.341737607},
{"learn":[4.582934052],"iteration":260,"passed_time":0.8241671615,"remaining_time":2.333561427},
{"learn":[4.582234842],"iteration":261,"passed_time":0.8255644279,"remaining_time":2.325444839},
{"learn":[4.57571562],"iteration":262,"passed_time":0.8268256517,"remaining_time":2.316998119},
{"learn":[4.571197349],"iteration":263,"passed_time":0.8281122714,"remaining_time":2.308676635},
{"learn":[4.56723703],"iteration":264,"passed_time":0.8293805058,"remaining_time":2.300357252},
{"learn":[4.560335567],"iteration":265,"passed_time":0.8306565744,"remaining_time":2.292112502},
{"learn":[4.554709345],"iteration":266,"passed_time":0.8320865894,"remaining_time":2.284342584},
{"learn":[4.552806306],"iteration":267,"passed_time":0.8333758842,"remaining_time":2.276235624},
{"learn":[4.550766241],"iteration":268,"passed_time":0.8350782887,"remaining_time":2.269301967},
{"learn":[4.549216045],"iteration":269,"passed_time":0.8367144125,"remaining_time":2.262227856},
{"learn":[4.547687452],"iteration":270,"passed_time":0.83831935,"remaining_time":2.255109986},
{"learn":[4.545642435],"iteration":271,"passed_time":0.8395978626,"remaining_time":2.247158985},
{"learn":[4.543930359],"iteration":272,"passed_time":0.8407892991,"remaining_time":2.239024983},
{"learn":[4.541029943],"iteration":273,"passed_time":0.8422633747,"remaining_time":2.231690548},
{"learn":[4.537781449],"iteration":274,"passed_time":0.844036964,"remaining_time":2.22518836},
{"learn":[4.53066128],"iteration":275,"passed_time":0.8455968208,"remaining_time":2.218159776},
{"learn":[4.526763956],"iteration":276,"passed_time":0.8468760311,"remaining_time":2.210438161},
{"learn":[4.522036004],"iteration":277,"passed_time":0.848915113,"remaining_time":2.204736373},
{"learn":[4.515307629],"iteration":278,"passed_time":0.8505201139,"remaining_time":2.197939076},
{"learn":[4.51109143],"iteration":279,"passed_time":0.8542986308,"remaining_time":2.196767908},
{"learn":[4.508233494],"iteration":280,"passed_time":0.855819083,"remaining_time":2.18980043},
{"learn":[4.502555629],"iteration":281,"passed_time":0.8590324029,"remaining_time":2.187181792},
{"learn":[4.500081355],"iteration":282,"passed_time":0.8606121273,"remaining_time":2.180420125},
{"learn":[4.495281743],"iteration":283,"passed_time":0.8621938709,"remaining_time":2.173700041},
{"learn":[4.492138869],"iteration":284,"passed_time":0.8643850832,"remaining_time":2.168545033},
{"learn":[4.491708261],"iteration":285,"passed_time":0.8664698584,"remaining_time":2.163145031},
{"learn":[4.489398865],"iteration":286,"passed_time":0.8689824959,"remaining_time":2.158831079},
{"learn":[4.485796373],"iteration":287,"passed_time":0.8706357926,"remaining_time":2.152405154},
{"learn":[4.479542205],"iteration":288,"passed_time":0.8726509287,"remaining_time":2.146902458},
{"learn":[4.475986993],"iteration":289,"passed_time":0.8743610901,"remaining_time":2.140677152},
{"learn":[4.468661855],"iteration":290,"passed_time":0.8759937589,"remaining_time":2.134294072},
{"learn":[4.463785664],"iteration":291,"passed_time":0.8776608597,"remaining_time":2.128027016},
{"learn":[4.460445831],"iteration":292,"passed_time":0.8791613539,"remaining_time":2.121389342},
{"learn":[4.45692492],"iteration":293,"passed_time":0.8821655992,"remaining_time":2.118397663},
{"learn":[4.454031688],"iteration":294,"passed_time":0.8835573259,"remaining_time":2.111552254},
{"learn":[4.451672391],"iteration":295,"passed_time":0.8849369169,"remaining_time":2.104714829},
{"learn":[4.45031553],"iteration":296,"passed_time":0.8863982068,"remaining_time":2.09810754},
{"learn":[4.446782666],"iteration":297,"passed_time":0.887770834,"remaining_time":2.091325924},
{"learn":[4.444369689],"iteration":298,"passed_time":0.8892790765,"remaining_time":2.084898437},
{"learn":[4.44411683],"iteration":299,"passed_time":0.8905495954,"remaining_time":2.077949056},
{"learn":[4.440876943],"iteration":300,"passed_time":0.8920589974,"remaining_time":2.071592157},
{"learn":[4.439336453],"iteration":301,"passed_time":0.8935731353,"remaining_time":2.065278306},
{"learn":[4.436666901],"iteration":302,"passed_time":0.8963981482,"remaining_time":2.062011582},
{"learn":[4.433043336],"iteration":303,"passed_time":0.8986395118,"remaining_time":2.057411514},
{"learn":[4.431419305],"iteration":304,"passed_time":0.9002350215,"remaining_time":2.051355213},
{"learn":[4.428859646],"iteration":305,"passed_time":0.9016735002,"remaining_time":2.044971925},
{"learn":[4.424552441],"iteration":306,"passed_time":0.9034983879,"remaining_time":2.039493104},
{"learn":[4.422706391],"iteration":307,"passed_time":0.9050658266,"remaining_time":2.033459584},
{"learn":[4.421427994],"iteration":308,"passed_time":0.9064285583,"remaining_time":2.026997197},
{"learn":[4.418733158],"iteration":309,"passed_time":0.9082653498,"remaining_time":2.021622875},
{"learn":[4.415656941],"iteration":310,"passed_time":0.9113714723,"remaining_time":2.019083423},
{"learn":[4.410747417],"iteration":311,"passed_time":0.9131311567,"remaining_time":2.013571269},
{"learn":[4.408126521],"iteration":312,"passed_time":0.9147232441,"remaining_time":2.007715236},
{"learn":[4.407843853],"iteration":313,"passed_time":0.916387118,"remaining_time":2.002043194},
{"learn":[4.405219398],"iteration":314,"passed_time":0.9179221614,"remaining_time":1.996116446},
{"learn":[4.402708465],"iteration":315,"passed_time":0.9197021696,"remaining_time":1.990747734},
{"learn":[4.40104971],"iteration":316,"passed_time":0.9214063008,"remaining_time":1.985238181},
{"learn":[4.400830038],"iteration":317,"passed_time":0.9231037299,"remaining_time":1.979738188},
{"learn":[4.39784288],"iteration":318,"passed_time":0.9245078128,"remaining_time":1.973635801},
{"learn":[4.393741845],"iteration":319,"passed_time":0.9296722722,"remaining_time":1.975553578},
{"learn":[4.393425936],"iteration":320,"passed_time":0.9318959403,"remaining_time":1.971206677},
{"learn":[4.390505974],"iteration":321,"passed_time":0.9334921564,"remaining_time":1.965551808},
{"learn":[4.390305136],"iteration":322,"passed_time":0.9353422972,"remaining_time":1.960454289},
{"learn":[4.38568203],"iteration":323,"passed_time":0.9389555443,"remaining_time":1.959055395},
{"learn":[4.383057135],"iteration":324,"passed_time":0.9425821553,"remaining_time":1.95767063},
{"learn":[4.380662684],"iteration":325,"passed_time":0.9444985624,"remaining_time":1.952736292},
{"learn":[4.37805727],"iteration":326,"passed_time":0.9461839703,"remaining_time":1.947344991},
{"learn":[4.373708319],"iteration":327,"passed_time":0.9480726069,"remaining_time":1.942392658},
{"learn":[4.36887921],"iteration":328,"passed_time":0.9499974347,"remaining_time":1.937532762},
{"learn":[4.367895929],"iteration":329,"passed_time":0.9515912169,"remaining_time":1.932018531},
{"learn":[4.362140573],"iteration":330,"passed_time":0.9530203934,"remaining_time":1.926195297},
{"learn":[4.361931924],"iteration":331,"passed_time":0.9588602669,"remaining_time":1.929273067},
{"learn":[4.359656377],"iteration":332,"passed_time":0.9609758709,"remaining_time":1.924837555},
{"learn":[4.354281355],"iteration":333,"passed_time":0.9626780425,"remaining_time":1.919591546},
{"learn":[4.348589447],"iteration":334,"passed_time":0.9644384745,"remaining_time":1.914482345},
{"learn":[4.346355698],"iteration":335,"passed_time":0.965909971,"remaining_time":1.908822086},
{"learn":[4.343894047],"iteration":336,"passed_time":0.9674436221,"remaining_time":1.903308966},
{"learn":[4.341561356],"iteration":337,"passed_time":0.9690082744,"remaining_time":1.897880111},
{"learn":[4.338869061],"iteration":338,"passed_time":0.9723756101,"remaining_time":1.895989021},
{"learn":[4.333720063],"iteration":339,"passed_time":0.9742384254,"remaining_time":1.891168708},
{"learn":[4.330892223],"iteration":340,"passed_time":0.9757784394,"remaining_time":1.885741911},
{"learn":[4.328311474],"iteration":341,"passed_time":0.9788153015,"remaining_time":1.883217744},
{"learn":[4.324580133],"iteration":342,"passed_time":0.9803738663,"remaining_time":1.87785898},
{"learn":[4.323354432],"iteration":343,"passed_time":0.9818910969,"remaining_time":1.872443487},
{"learn":[4.323159553],"iteration":344,"passed_time":0.9833341634,"remaining_time":1.866909788},
{"learn":[4.318639682],"iteration":345,"passed_time":0.9846248006,"remaining_time":1.861111617},
{"learn":[4.312712208],"iteration":346,"passed_time":0.9872108046,"remaining_time":1.857777105},
{"learn":[4.311461062],"iteration":347,"passed_time":0.9887035171,"remaining_time":1.852398543},
{"learn":[4.311178356],"iteration":348,"passed_time":0.9900808681,"remaining_time":1.846827064},
{"learn":[4.311102505],"iteration":349,"passed_time":0.9912777905,"remaining_time":1.840944468},
{"learn":[4.310232308],"iteration":350,"passed_time":0.9924729021,"remaining_time":1.835085224},
{"learn":[4.305128197],"iteration":351,"passed_time":0.9937218918,"remaining_time":1.829351665},
{"learn":[4.304595496],"iteration":352,"passed_time":0.9949639613,"remaining_time":1.82363083},
{"learn":[4.3004992],"iteration":353,"passed_time":0.9963619876,"remaining_time":1.818219898},
{"learn":[4.297581524],"iteration":354,"passed_time":0.9977004045,"remaining_time":1.81272327},
{"learn":[4.297355825],"iteration":355,"passed_time":0.9989081368,"remaining_time":1.807013596},
{"learn":[4.295758715],"iteration":356,"passed_time":1.000990291,"remaining_time":1.802904082},
{"learn":[4.292500657],"iteration":357,"passed_time":1.002735106,"remaining_time":1.798200944},
{"learn":[4.290797586],"iteration":358,"passed_time":1.004357811,"remaining_time":1.793296259},
{"learn":[4.286410608],"iteration":359,"passed_time":1.005704448,"remaining_time":1.787919019},
{"learn":[4.280278245],"iteration":360,"passed_time":1.006953219,"remaining_time":1.782390878},
{"learn":[4.279941283],"iteration":361,"passed_time":1.008198632,"remaining_time":1.776880462},
{"learn":[4.274426275],"iteration":362,"passed_time":1.009545067,"remaining_time":1.771570821},
{"learn":[4.273567658],"iteration":363,"passed_time":1.010804254,"remaining_time":1.766130509},
{"learn":[4.269488271],"iteration":364,"passed_time":1.012045866,"remaining_time":1.760682534},
{"learn":[4.266838205],"iteration":365,"passed_time":1.01333789,"remaining_time":1.75534487},
{"learn":[4.263456509],"iteration":366,"passed_time":1.014645556,"remaining_time":1.750056232},
{"learn":[4.260360204],"iteration":367,"passed_time":1.016697442,"remaining_time":1.746067347},
{"learn":[4.255120549],"iteration":368,"passed_time":1.018058365,"remaining_time":1.740907395},
{"learn":[4.252582211],"iteration":369,"passed_time":1.019349759,"remaining_time":1.735649589},
{"learn":[4.247857931],"iteration":370,"passed_time":1.020646501,"remaining_time":1.730422235},
{"learn":[4.245288911],"iteration":371,"passed_time":1.021975878,"remaining_time":1.725271106},
{"learn":[4.24048515],"iteration":372,"passed_time":1.023260723,"remaining_time":1.720065613},
{"learn":[4.2378365],"iteration":373,"passed_time":1.024553342,"remaining_time":1.714894096},
{"learn":[4.236751063],"iteration":374,"passed_time":1.025855372,"remaining_time":1.709758953},
{"learn":[4.233240093],"iteration":375,"passed_time":1.027162581,"remaining_time":1.704652794},
{"learn":[4.230358421],"iteration":376,"passed_time":1.028584863,"remaining_time":1.699756949},
{"learn":[4.225853583],"iteration":377,"passed_time":1.031153284,"remaining_time":1.696765457},
{"learn":[4.224702126],"iteration":378,"passed_time":1.032550185,"remaining_time":1.691856636},
{"learn":[4.224361982],"iteration":379,"passed_time":1.033827723,"remaining_time":1.686771549},
{"learn":[4.223787954],"iteration":380,"passed_time":1.035164572,"remaining_time":1.681802809},
{"learn":[4.22144054],"iteration":381,"passed_time":1.036478227,"remaining_time":1.676815561},
{"learn":[4.217739335],"iteration":382,"passed_time":1.037740413,"remaining_time":1.671764581},
{"learn":[4.215611665],"iteration":383,"passed_time":1.038970051,"remaining_time":1.666681123},
{"learn":[4.210236863],"iteration":384,"passed_time":1.04026788,"remaining_time":1.661726613},
{"learn":[4.208454294],"iteration":385,"passed_time":1.041743981,"remaining_time":1.657074622},
{"learn":[4.207446501],"iteration":386,"passed_time":1.042997482,"remaining_time":1.65208645},
{"learn":[4.204985442],"iteration":387,"passed_time":1.045799537,"remaining_time":1.649560095},
{"learn":[4.202796622],"iteration":388,"passed_time":1.04745677,"remaining_time":1.645234155},
{"learn":[4.199774004],"iteration":389,"passed_time":1.048831705,"remaining_time":1.64048036},
{"learn":[4.199458358],"iteration":390,"passed_time":1.05008015,"remaining_time":1.635546831},
{"learn":[4.19751254],"iteration":391,"passed_time":1.051344947,"remaining_time":1.630657469},
{"learn":[4.195201346],"iteration":392,"passed_time":1.052604036,"remaining_time":1.625777735},
{"learn":[4.190593508],"iteration":393,"passed_time":1.053820023,"remaining_time":1.620850086},
{"learn":[4.187212054],"iteration":394,"passed_time":1.05522372,"remaining_time":1.616228736},
{"learn":[4.184984466],"iteration":395,"passed_time":1.056519509,"remaining_time":1.61145905},
{"learn":[4.182832144],"iteration":396,"passed_time":1.057769687,"remaining_time":1.606637585},
{"learn":[4.179752812],"iteration":397,"passed_time":1.060731223,"remaining_time":1.604422604},
{"learn":[4.17878934],"iteration":398,"passed_time":1.062645768,"remaining_time":1.600626833},
{"learn":[4.174548229],"iteration":399,"passed_time":1.063994475,"remaining_time":1.595991713},
{"learn":[4.168872556],"iteration":400,"passed_time":1.065285108,"remaining_time":1.591286234},
{"learn":[4.163926494],"iteration":401,"passed_time":1.06669894,"remaining_time":1.58678101},
{"learn":[4.159485076],"iteration":402,"passed_time":1.068150707,"remaining_time":1.582347325},
{"learn":[4.155926102],"iteration":403,"passed_time":1.06943996,"remaining_time":1.577688654},
{"learn":[4.153540115],"iteration":404,"passed_time":1.070725634,"remaining_time":1.573041364},
{"learn":[4.150983044],"iteration":405,"passed_time":1.072004776,"remaining_time":1.568401076},
{"learn":[4.146539132],"iteration":406,"passed_time":1.073779861,"remaining_time":1.564499896},
{"learn":[4.144869174],"iteration":407,"passed_time":1.075449246,"remaining_time":1.560455768},
{"learn":[4.142825962],"iteration":408,"passed_time":1.076718135,"remaining_time":1.555844543},
{"learn":[4.142467378],"iteration":409,"passed_time":1.077884124,"remaining_time":1.551101545},
{"learn":[4.141800768],"iteration":410,"passed_time":1.079075454,"remaining_time":1.546412269},
{"learn":[4.140107084],"iteration":411,"passed_time":1.080359432,"remaining_time":1.541872199},
{"learn":[4.136243196],"iteration":412,"passed_time":1.08163744,"remaining_time":1.537339413},
{"learn":[4.133618439],"iteration":413,"passed_time":1.082912447,"remaining_time":1.532818101},
{"learn":[4.131053025],"iteration":414,"passed_time":1.084199575,"remaining_time":1.528329522},
{"learn":[4.128379975],"iteration":415,"passed_time":1.085502433,"remaining_time":1.523878415},
{"learn":[4.127068571],"iteration":416,"passed_time":1.088524394,"remaining_time":1.521845855},
{"learn":[4.125969877],"iteration":417,"passed_time":1.09091375,"remaining_time":1.518927757},
{"learn":[4.123893633],"iteration":418,"passed_time":1.092479794,"remaining_time":1.51487055},
{"learn":[4.119643722],"iteration":419,"passed_time":1.094136025,"remaining_time":1.510949749},
{"learn":[4.11465686],"iteration":420,"passed_time":1.095468147,"remaining_time":1.50659396},
{"learn":[4.111565986],"iteration":421,"passed_time":1.096759574,"remaining_time":1.502196763},
{"learn":[4.106322452],"iteration":422,"passed_time":1.098069313,"remaining_time":1.497839228},
{"learn":[4.104222175],"iteration":423,"passed_time":1.099405178,"remaining_time":1.493531563},
{"learn":[4.103008002],"iteration":424,"passed_time":1.100681244,"remaining_time":1.489156978},
{"learn":[4.099176337],"iteration":425,"passed_time":1.103181714,"remaining_time":1.486446722},
{"learn":[4.096525716],"iteration":426,"passed_time":1.104747036,"remaining_time":1.482482557},
{"learn":[4.094967724],"iteration":427,"passed_time":1.106207538,"remaining_time":1.478389513},
{"learn":[4.094683584],"iteration":428,"passed_time":1.107402403,"remaining_time":1.47395518},
{"learn":[4.091096563],"iteration":429,"passed_time":1.108651424,"remaining_time":1.469607702},
{"learn":[4.089178677],"iteration":430,"passed_time":1.109910211,"remaining_time":1.465287494},
{"learn":[4.085335077],"iteration":431,"passed_time":1.111239636,"remaining_time":1.461074336},
{"learn":[4.084852122],"iteration":432,"passed_time":1.112663257,"remaining_time":1.456997844},
{"learn":[4.080322952],"iteration":433,"passed_time":1.113962188,"remaining_time":1.452770964},
{"learn":[4.077449519],"iteration":434,"passed_time":1.115255209,"remaining_time":1.448549869},
{"learn":[4.076568374],"iteration":435,"passed_time":1.118246172,"remaining_time":1.446538626},
{"learn":[4.076071793],"iteration":436,"passed_time":1.119862705,"remaining_time":1.442752181},
{"learn":[4.075027644],"iteration":437,"passed_time":1.121180094,"remaining_time":1.43859181},
{"learn":[4.07020837],"iteration":438,"passed_time":1.122518394,"remaining_time":1.434471114},
{"learn":[4.06833694],"iteration":439,"passed_time":1.123813858,"remaining_time":1.430308546},
{"learn":[4.063936568],"iteration":440,"passed_time":1.125462682,"remaining_time":1.426606891},
{"learn":[4.061734926],"iteration":441,"passed_time":1.126823079,"remaining_time":1.422550403},
{"learn":[4.060815619],"iteration":442,"passed_time":1.128232076,"remaining_time":1.418567192},
{"learn":[4.056407489],"iteration":443,"passed_time":1.12957423,"remaining_time":1.414511873},
{"learn":[4.05238936],"iteration":444,"passed_time":1.132286883,"remaining_time":1.412178022},
{"learn":[4.049685254],"iteration":445,"passed_time":1.13390642,"remaining_time":1.408484656},
{"learn":[4.045162016],"iteration":446,"passed_time":1.135248768,"remaining_time":1.404457648},
{"learn":[4.042955482],"iteration":447,"passed_time":1.136499435,"remaining_time":1.400329661},
{"learn":[4.041467663],"iteration":448,"passed_time":1.137778749,"remaining_time":1.396249645},
{"learn":[4.038920476],"iteration":449,"passed_time":1.139135116,"remaining_time":1.392276253},
{"learn":[4.036694383],"iteration":450,"passed_time":1.140457179,"remaining_time":1.388272708},
{"learn":[4.034999007],"iteration":451,"passed_time":1.141720758,"remaining_time":1.384210123},
{"learn":[4.031928018],"iteration":452,"passed_time":1.143005955,"remaining_time":1.380185998},
{"learn":[4.028718143],"iteration":453,"passed_time":1.14427794,"remaining_time":1.376158051},
{"learn":[4.027401978],"iteration":454,"passed_time":1.14605255,"remaining_time":1.372744263},
{"learn":[4.025930598],"iteration":455,"passed_time":1.148111523,"remaining_time":1.369676905},
{"learn":[4.021074523],"iteration":456,"passed_time":1.149416714,"remaining_time":1.365718328},
{"learn":[4.020268486],"iteration":457,"passed_time":1.150647308,"remaining_time":1.361683059},
{"learn":[4.017986361],"iteration":458,"passed_time":1.152136687,"remaining_time":1.357965028},
{"learn":[4.014814804],"iteration":459,"passed_time":1.153393343,"remaining_time":1.35398349},
{"learn":[4.009704796],"iteration":460,"passed_time":1.154668406,"remaining_time":1.350035294},
{"learn":[4.008440457],"iteration":461,"passed_time":1.155908835,"remaining_time":1.34605834},
{"learn":[4.004854849],"iteration":462,"passed_time":1.157212528,"remaining_time":1.342166582},
{"learn":[4.000898028],"iteration":463,"passed_time":1.158627272,"remaining_time":1.338414262},
{"learn":[3.996617985],"iteration":464,"passed_time":1.159885096,"remaining_time":1.334491455},
{"learn":[3.995443319],"iteration":465,"passed_time":1.162154533,"remaining_time":1.331739315},
{"learn":[3.990771995],"iteration":466,"passed_time":1.163653962,"remaining_time":1.328110411},
{"learn":[3.989249359],"iteration":467,"passed_time":1.164991712,"remaining_time":1.324306818},
{"learn":[3.986599538],"iteration":468,"passed_time":1.166297462,"remaining_time":1.32047751},
{"learn":[3.985628919],"iteration":469,"passed_time":1.167558707,"remaining_time":1.316608754},
{"learn":[3.985086112],"iteration":470,"passed_time":1.168786376,"remaining_time":1.312713361},
{"learn":[3.98466839],"iteration":471,"passed_time":1.170022996,"remaining_time":1.308839284},
{"learn":[3.984233894],"iteration":472,"passed_time":1.171395883,"remaining_time":1.305128183},
{"learn":[3.981855845],"iteration":473,"passed_time":1.172661668,"remaining_time":1.301308096},
{"learn":[3.978684264],"iteration":474,"passed_time":1.173922785,"remaining_time":1.297493605},
{"learn":[3.974361269],"iteration":475,"passed_time":1.177973976,"remaining_time":1.296761268},
{"learn":[3.972074049],"iteration":476,"passed_time":1.179323835,"remaining_time":1.293053177},
{"learn":[3.97191982],"iteration":477,"passed_time":1.180811828,"remaining_time":1.289505803},
{"learn":[3.969616848],"iteration":478,"passed_time":1.182127087,"remaining_time":1.285779148},
{"learn":[3.968533527],"iteration":479,"passed_time":1.183386409,"remaining_time":1.282001943},
{"learn":[3.967568753],"iteration":480,"passed_time":1.184777258,"remaining_time":1.278377124},
{"learn":[3.966232553],"iteration":481,"passed_time":1.186052793,"remaining_time":1.274637649},
{"learn":[3.961522393],"iteration":482,"passed_time":1.187332934,"remaining_time":1.270913306},
{"learn":[3.955829553],"iteration":483,"passed_time":1.188583934,"remaining_time":1.267167996},
{"learn":[3.954248095],"iteration":484,"passed_time":1.191144992,"remaining_time":1.264824064},
{"learn":[3.951922606],"iteration":485,"passed_time":1.192562152,"remaining_time":1.261269437},
{"learn":[3.94978202],"iteration":486,"passed_time":1.194006718,"remaining_time":1.257752457},
{"learn":[3.949518999],"iteration":487,"passed_time":1.195379667,"remaining_time":1.254168831},
{"learn":[3.945431216],"iteration":488,"passed_time":1.196796508,"remaining_time":1.250640114},
{"learn":[3.943249086],"iteration":489,"passed_time":1.198228022,"remaining_time":1.247135289},
{"learn":[3.941981548],"iteration":490,"passed_time":1.199563633,"remaining_time":1.24353949},
{"learn":[3.936600517],"iteration":491,"passed_time":1.200874439,"remaining_time":1.239927266},
{"learn":[3.934476885],"iteration":492,"passed_time":1.202287995,"remaining_time":1.236430048},
{"learn":[3.93045798],"iteration":493,"passed_time":1.206046797,"remaining_time":1.23534348},
{"learn":[3.925977375],"iteration":494,"passed_time":1.207686591,"remaining_time":1.2320843},
{"learn":[3.92457993],"iteration":495,"passed_time":1.209327264,"remaining_time":1.228832543},
{"learn":[3.919849146],"iteration":496,"passed_time":1.211553094,"remaining_time":1.22617949},
{"learn":[3.919681964],"iteration":497,"passed_time":1.212892342,"remaining_time":1.222634449},
{"learn":[3.917633027],"iteration":498,"passed_time":1.214191664,"remaining_time":1.219058163},
{"learn":[3.916616419],"iteration":499,"passed_time":1.215516636,"remaining_time":1.215516636},
{"learn":[3.912896166],"iteration":500,"passed_time":1.2167929,"remaining_time":1.211935444},
{"learn":[3.912769674],"iteration":501,"passed_time":1.218364205,"remaining_time":1.208656123},
{"learn":[3.909373788],"iteration":502,"passed_time":1.222961857,"remaining_time":1.208373842},
{"learn":[3.906706036],"iteration":503,"passed_time":1.224448431,"remaining_time":1.205012741},
{"learn":[3.903895664],"iteration":504,"passed_time":1.225770353,"remaining_time":1.201497673},
{"learn":[3.902982967],"iteration":505,"passed_time":1.227036593,"remaining_time":1.197936911},
{"learn":[3.900905528],"iteration":506,"passed_time":1.228306843,"remaining_time":1.1943891},
{"learn":[3.897463465],"iteration":507,"passed_time":1.229562446,"remaining_time":1.19083607},
{"learn":[3.895918033],"iteration":508,"passed_time":1.231025725,"remaining_time":1.187492399},
{"learn":[3.893921936],"iteration":509,"passed_time":1.2323425,"remaining_time":1.184015343},
{"learn":[3.890237934],"iteration":510,"passed_time":1.233588652,"remaining_time":1.18047916},
{"learn":[3.887311613],"iteration":511,"passed_time":1.237231161,"remaining_time":1.17923595},
{"learn":[3.884869735],"iteration":512,"passed_time":1.238665429,"remaining_time":1.175887064},
{"learn":[3.882101231],"iteration":513,"passed_time":1.239941837,"remaining_time":1.172396368},
{"learn":[3.88060368],"iteration":514,"passed_time":1.241238088,"remaining_time":1.168932957},
{"learn":[3.877726076],"iteration":515,"passed_time":1.242587716,"remaining_time":1.165528013},
{"learn":[3.874938145],"iteration":516,"passed_time":1.243976346,"remaining_time":1.162167457},
{"learn":[3.874340833],"iteration":517,"passed_time":1.245257987,"remaining_time":1.158714961},
{"learn":[3.873105224],"iteration":518,"passed_time":1.24654378,"remaining_time":1.155274678},
{"learn":[3.869800236],"iteration":519,"passed_time":1.247832248,"remaining_time":1.151845152},
{"learn":[3.867932518],"iteration":520,"passed_time":1.251361946,"remaining_time":1.1504844},
{"learn":[3.866666962],"iteration":521,"passed_time":1.252907493,"remaining_time":1.147298432},
{"learn":[3.865527652],"iteration":522,"passed_time":1.254219261,"remaining_time":1.143905521},
{"learn":[3.861900081],"iteration":523,"passed_time":1.255604659,"remaining_time":1.140587439},
{"learn":[3.858502887],"iteration":524,"passed_time":1.256871748,"remaining_time":1.137169677},
{"learn":[3.858335097],"iteration":525,"passed_time":1.258109474,"remaining_time":1.133733632},
{"learn":[3.855719306],"iteration":526,"passed_time":1.259370319,"remaining_time":1.130326681},
{"learn":[3.855137428],"iteration":527,"passed_time":1.260613367,"remaining_time":1.126911949},
{"learn":[3.851985706],"iteration":528,"passed_time":1.26196433,"remaining_time":1.123601511},
{"learn":[3.851051809],"iteration":529,"passed_time":1.263184967,"remaining_time":1.120182896},
{"learn":[3.850679146],"iteration":530,"passed_time":1.265868128,"remaining_time":1.118064317},
{"learn":[3.848179484],"iteration":531,"passed_time":1.267340453,"remaining_time":1.114878444},
{"learn":[3.844551071],"iteration":532,"passed_time":1.268758756,"remaining_time":1.111651668},
{"learn":[3.841604794],"iteration":533,"passed_time":1.270040763,"remaining_time":1.108312726},
{"learn":[3.83969656],"iteration":534,"passed_time":1.271330993,"remaining_time":1.104988621},
{"learn":[3.836811463],"iteration":535,"passed_time":1.272596444,"remaining_time":1.101650653},
{"learn":[3.834182551],"iteration":536,"passed_time":1.273835215,"remaining_time":1.098297402},
{"learn":[3.828012842],"iteration":537,"passed_time":1.27513547,"remaining_time":1.095004809},
{"learn":[3.826636176],"iteration":538,"passed_time":1.276417883,"remaining_time":1.091704349},
{"learn":[3.826189798],"iteration":539,"passed_time":1.277693561,"remaining_time":1.088405626},
{"learn":[3.824104738],"iteration":540,"passed_time":1.280329702,"remaining_time":1.086268638},
{"learn":[3.82300218],"iteration":541,"passed_time":1.281736104,"remaining_time":1.083090656},
{"learn":[3.817146402],"iteration":542,"passed_time":1.283042026,"remaining_time":1.079834634},
{"learn":[3.814638044],"iteration":543,"passed_time":1.284395859,"remaining_time":1.076625941},
{"learn":[3.812979573],"iteration":544,"passed_time":1.285701014,"remaining_time":1.073383415},
{"learn":[3.811938825],"iteration":545,"passed_time":1.286954567,"remaining_time":1.07010508},
{"learn":[3.811479418],"iteration":546,"passed_time":1.288147529,"remaining_time":1.066783969},
{"learn":[3.80742981],"iteration":547,"passed_time":1.289462133,"remaining_time":1.063570957},
{"learn":[3.805097043],"iteration":548,"passed_time":1.290821739,"remaining_time":1.060401829},
{"learn":[3.801577232],"iteration":549,"passed_time":1.292102254,"remaining_time":1.057174572},
{"learn":[3.799762083],"iteration":550,"passed_time":1.294829976,"remaining_time":1.055133683},
{"learn":[3.796393455],"iteration":551,"passed_time":1.296252827,"remaining_time":1.05203128},
{"learn":[3.793486459],"iteration":552,"passed_time":1.29767981,"remaining_time":1.048938292},
{"learn":[3.792006091],"iteration":553,"passed_time":1.298950454,"remaining_time":1.045725456},
{"learn":[3.78932128],"iteration":554,"passed_time":1.300209862,"remaining_time":1.04251061},
{"learn":[3.787581812],"iteration":555,"passed_time":1.301415609,"remaining_time":1.039259947},
{"learn":[3.785308865],"iteration":556,"passed_time":1.302697229,"remaining_time":1.036076971},
{"learn":[3.78465475],"iteration":557,"passed_time":1.304081955,"remaining_time":1.032982481},
{"learn":[3.780498869],"iteration":558,"passed_time":1.305549859,"remaining_time":1.029959727},
{"learn":[3.778734909],"iteration":559,"passed_time":1.307319718,"remaining_time":1.027179779},
{"learn":[3.778652349],"iteration":560,"passed_time":1.310156813,"remaining_time":1.025238576},
{"learn":[3.777928006],"iteration":561,"passed_time":1.311618255,"remaining_time":1.022222057},
{"learn":[3.776131406],"iteration":562,"passed_time":1.312934292,"remaining_time":1.019098198},
{"learn":[3.772925617],"iteration":563,"passed_time":1.314286822,"remaining_time":1.016008961},
{"learn":[3.7727745],"iteration":564,"passed_time":1.315609802,"remaining_time":1.012903122},
{"learn":[3.771763073],"iteration":565,"passed_time":1.317041371,"remaining_time":1.009886846},
{"learn":[3.768738162],"iteration":566,"passed_time":1.318350618,"remaining_time":1.006782747},
{"learn":[3.767220794],"iteration":567,"passed_time":1.319681681,"remaining_time":1.00370156},
{"learn":[3.766691102],"iteration":568,"passed_time":1.32091356,"remaining_time":1.000551396},
{"learn":[3.766259335],"iteration":569,"passed_time":1.322314758,"remaining_time":0.9975356943},
{"learn":[3.76116362],"iteration":570,"passed_time":1.324915523,"remaining_time":0.995426899},
{"learn":[3.758633056],"iteration":571,"passed_time":1.326254568,"remaining_time":0.9923722992},
{"learn":[3.754603809],"iteration":572,"passed_time":1.327520952,"remaining_time":0.98926954},
{"learn":[3.754070549],"iteration":573,"passed_time":1.328806201,"remaining_time":0.9861871802},
{"learn":[3.750534319],"iteration":574,"passed_time":1.330283324,"remaining_time":0.983252892},
{"learn":[3.746491516],"iteration":575,"passed_time":1.331653889,"remaining_time":0.9802452239},
{"learn":[3.744210544],"iteration":576,"passed_time":1.332952574,"remaining_time":0.9771905354},
{"learn":[3.742929991],"iteration":577,"passed_time":1.334223053,"remaining_time":0.9741213292},
{"learn":[3.740402992],"iteration":578,"passed_time":1.335534442,"remaining_time":0.9710880831},
{"learn":[3.739644243],"iteration":579,"passed_time":1.33689987,"remaining_time":0.968099906},
{"learn":[3.737529404],"iteration":580,"passed_time":1.339018003,"remaining_time":0.9656601432},
{"learn":[3.737196923],"iteration":581,"passed_time":1.340322597,"remaining_time":0.9626371917},
{"learn":[3.733954464],"iteration":582,"passed_time":1.341735464,"remaining_time":0.9596975788},
{"learn":[3.731608623],"iteration":583,"passed_time":1.343164837,"remaining_time":0.9567749525},
{"learn":[3.729843952],"iteration":584,"passed_time":1.344525176,"remaining_time":0.9538084579},
{"learn":[3.727223798],"iteration":585,"passed_time":1.345774076,"remaining_time":0.9507687157},
{"learn":[3.725351667],"iteration":586,"passed_time":1.347057907,"remaining_time":0.9477596515},
{"learn":[3.725026912],"iteration":587,"passed_time":1.348442701,"remaining_time":0.9448271989},
{"learn":[3.721974565],"iteration":588,"passed_time":1.349900149,"remaining_time":0.9419506981},
{"learn":[3.720269493],"iteration":589,"passed_time":1.351197679,"remaining_time":0.9389678789},
{"learn":[3.718907466],"iteration":590,"passed_time":1.353565069,"remaining_time":0.9367311563},
{"learn":[3.715602912],"iteration":591,"passed_time":1.355011165,"remaining_time":0.9338590462},
{"learn":[3.714463059],"iteration":592,"passed_time":1.356329505,"remaining_time":0.9309040617},
{"learn":[3.710802077],"iteration":593,"passed_time":1.357623122,"remaining_time":0.9279376891},
{"learn":[3.708032435],"iteration":594,"passed_time":1.35886534,"remaining_time":0.9249419544},
{"learn":[3.703788939],"iteration":595,"passed_time":1.360097578,"remaining_time":0.9219453382},
{"learn":[3.702500944],"iteration":596,"passed_time":1.361329636,"remaining_time":0.9189545115},
{"learn":[3.698196925],"iteration":597,"passed_time":1.362731275,"remaining_time":0.9160835661},
{"learn":[3.69658891],"iteration":598,"passed_time":1.364045962,"remaining_time":0.913159317},
{"learn":[3.696124066],"iteration":599,"passed_time":1.365294795,"remaining_time":0.9101965298},
{"learn":[3.693537052],"iteration":600,"passed_time":1.368497733,"remaining_time":0.9085367645},
{"learn":[3.691343275],"iteration":601,"passed_time":1.370611337,"remaining_time":0.9061516812},
{"learn":[3.690973831],"iteration":602,"passed_time":1.372525153,"remaining_time":0.9036359629},
{"learn":[3.686151073],"iteration":603,"passed_time":1.373872341,"remaining_time":0.9007507401},
{"learn":[3.683921982],"iteration":604,"passed_time":1.37516194,"remaining_time":0.8978330023},
{"learn":[3.679975271],"iteration":605,"passed_time":1.376448385,"remaining_time":0.8949185866},
{"learn":[3.674047638],"iteration":606,"passed_time":1.377797575,"remaining_time":0.8920501598},
{"learn":[3.673151794],"iteration":607,"passed_time":1.379091167,"remaining_time":0.8891508841},
{"learn":[3.670953108],"iteration":608,"passed_time":1.380361772,"remaining_time":0.8862421227},
{"learn":[3.6703947],"iteration":609,"passed_time":1.382887718,"remaining_time":0.8841413282},
{"learn":[3.668433805],"iteration":610,"passed_time":1.384368443,"remaining_time":0.8813736897},
{"learn":[3.668304956],"iteration":611,"passed_time":1.385585404,"remaining_time":0.8784430341},
{"learn":[3.667880012],"iteration":612,"passed_time":1.38692636,"remaining_time":0.8755962503},
{"learn":[3.667282264],"iteration":613,"passed_time":1.388125874,"remaining_time":0.8726654514},
{"learn":[3.664611483],"iteration":614,"passed_time":1.389433771,"remaining_time":0.8698081331},
{"learn":[3.662543394],"iteration":615,"passed_time":1.390705034,"remaining_time":0.8669330083},
{"learn":[3.659041959],"iteration":616,"passed_time":1.392060385,"remaining_time":0.8641152798},
{"learn":[3.656868545],"iteration":617,"passed_time":1.39343263,"remaining_time":0.8613127257},
{"learn":[3.654785614],"iteration":618,"passed_time":1.394742365,"remaining_time":0.8584763181},
{"learn":[3.654566096],"iteration":619,"passed_time":1.397579707,"remaining_time":0.8565811105},
{"learn":[3.651007045],"iteration":620,"passed_time":1.398972811,"remaining_time":0.8538014415},
{"learn":[3.648921786],"iteration":621,"passed_time":1.400318621,"remaining_time":0.8509974901},
{"learn":[3.647655706],"iteration":622,"passed_time":1.401812674,"remaining_time":0.8482879263},
{"learn":[3.647241144],"iteration":623,"passed_time":1.403129026,"remaining_time":0.8454751823},
{"learn":[3.644195689],"iteration":624,"passed_time":1.404426332,"remaining_time":0.8426557994},
{"learn":[3.642632246],"iteration":625,"passed_time":1.405724493,"remaining_time":0.8398417896},
{"learn":[3.642523322],"iteration":626,"passed_time":1.406811975,"remaining_time":0.8369072835},
{"learn":[3.641494659],"iteration":627,"passed_time":1.408160547,"remaining_time":0.8341333179},
{"learn":[3.63976496],"iteration":628,"passed_time":1.409599931,"remaining_time":0.8314174477},
{"learn":[3.637945652],"iteration":629,"passed_time":1.411966819,"remaining_time":0.8292503539},
{"learn":[3.636233667],"iteration":630,"passed_time":1.413328344,"remaining_time":0.8264947052},
{"learn":[3.635304404],"iteration":631,"passed_time":1.414714149,"remaining_time":0.8237576057},
{"learn":[3.632234951],"iteration":632,"passed_time":1.4160416,"remaining_time":0.8209909434},
{"learn":[3.631630987],"iteration":633,"passed_time":1.417359801,"remaining_time":0.8182234815},
{"learn":[3.630301009],"iteration":634,"passed_time":1.418686773,"remaining_time":0.8154656252},
{"learn":[3.629077964],"iteration":635,"passed_time":1.419967187,"remaining_time":0.8126856228},
{"learn":[3.628004522],"iteration":636,"passed_time":1.421660216,"remaining_time":0.8101454604},
{"learn":[3.625062876],"iteration":637,"passed_time":1.423003772,"remaining_time":0.8074096636},
{"learn":[3.624917986],"iteration":638,"passed_time":1.424251449,"remaining_time":0.8046240578},
{"learn":[3.622887087],"iteration":639,"passed_time":1.426615385,"remaining_time":0.8024711543},
{"learn":[3.621220865],"iteration":640,"passed_time":1.42831084,"remaining_time":0.7999432008},
{"learn":[3.621143844],"iteration":641,"passed_time":1.430066437,"remaining_time":0.7974513777},
{"learn":[3.620822821],"iteration":642,"passed_time":1.431320113,"remaining_time":0.7946831733},
{"learn":[3.619202826],"iteration":643,"passed_time":1.432639706,"remaining_time":0.7919561108},
{"learn":[3.618204882],"iteration":644,"passed_time":1.433989422,"remaining_time":0.7892499918},
{"learn":[3.614259666],"iteration":645,"passed_time":1.435470146,"remaining_time":0.7866198633},
{"learn":[3.613415661],"iteration":646,"passed_time":1.43680462,"remaining_time":0.7839134945},
{"learn":[3.611096773],"iteration":647,"passed_time":1.438081507,"remaining_time":0.7811800781},
{"learn":[3.610820695],"iteration":648,"passed_time":1.440509635,"remaining_time":0.7790737778},
{"learn":[3.609290065],"iteration":649,"passed_time":1.442235939,"remaining_time":0.7765885826},
{"learn":[3.60897947],"iteration":650,"passed_time":1.443665426,"remaining_time":0.7739465956},
{"learn":[3.606570702],"iteration":651,"passed_time":1.445107813,"remaining_time":0.771315213},
{"learn":[3.606292637],"iteration":652,"passed_time":1.446485233,"remaining_time":0.7686529495},
{"learn":[3.602753838],"iteration":653,"passed_time":1.448110536,"remaining_time":0.7661257578},
{"learn":[3.599755869],"iteration":654,"passed_time":1.44956015,"remaining_time":0.7635087811},
{"learn":[3.599509575],"iteration":655,"passed_time":1.450935013,"remaining_time":0.7608561652},
{"learn":[3.595337722],"iteration":656,"passed_time":1.452337354,"remaining_time":0.7582217846},
{"learn":[3.595168561],"iteration":657,"passed_time":1.456651983,"remaining_time":0.7571048301},
{"learn":[3.59290559],"iteration":658,"passed_time":1.459475682,"remaining_time":0.7552066881},
{"learn":[3.592015928],"iteration":659,"passed_time":1.462929892,"remaining_time":0.7536305505},
{"learn":[3.590680403],"iteration":660,"passed_time":1.464976007,"remaining_time":0.7513265753},
{"learn":[3.590361532],"iteration":661,"passed_time":1.466307833,"remaining_time":0.7486586822},
{"learn":[3.589069739],"iteration":662,"passed_time":1.468635372,"remaining_time":0.7465009357},
{"learn":[3.585010186],"iteration":663,"passed_time":1.471359724,"remaining_time":0.7445434748},
{"learn":[3.582997552],"iteration":664,"passed_time":1.473263662,"remaining_time":0.7421704162},
{"learn":[3.582119256],"iteration":665,"passed_time":1.474791341,"remaining_time":0.739610072},
{"learn":[3.579019356],"iteration":666,"passed_time":1.476368054,"remaining_time":0.7370773044},
{"learn":[3.57719559],"iteration":667,"passed_time":1.477759066,"remaining_time":0.7344551048},
{"learn":[3.574050046],"iteration":668,"passed_time":1.47927618,"remaining_time":0.7318989772},
{"learn":[3.572204518],"iteration":669,"passed_time":1.481016596,"remaining_time":0.7294559355},
{"learn":[3.569508025],"iteration":670,"passed_time":1.482411908,"remaining_time":0.7268457788},
{"learn":[3.566268704],"iteration":671,"passed_time":1.483795142,"remaining_time":0.7242333431},
{"learn":[3.562564052],"iteration":672,"passed_time":1.486046583,"remaining_time":0.7220464081},
{"learn":[3.561173586],"iteration":673,"passed_time":1.488285704,"remaining_time":0.7198533228},
{"learn":[3.559551904],"iteration":674,"passed_time":1.490086252,"remaining_time":0.7174489364},
{"learn":[3.558593054],"iteration":675,"passed_time":1.491595381,"remaining_time":0.714906662},
{"learn":[3.555647008],"iteration":676,"passed_time":1.49294395,"remaining_time":0.712290836},
{"learn":[3.553100059],"iteration":677,"passed_time":1.494236683,"remaining_time":0.7096522301},
{"learn":[3.55085578],"iteration":678,"passed_time":1.495894776,"remaining_time":0.707190314},
{"learn":[3.550737965],"iteration":679,"passed_time":1.497443582,"remaining_time":0.7046793325},
{"learn":[3.549408772],"iteration":680,"passed_time":1.501347171,"remaining_time":0.7032742254},
{"learn":[3.547390589],"iteration":681,"passed_time":1.502730363,"remaining_time":0.7006865916},
{"learn":[3.54723575],"iteration":682,"passed_time":1.503952727,"remaining_time":0.6980278394},
{"learn":[3.543988891],"iteration":683,"passed_time":1.505290289,"remaining_time":0.695426508},
{"learn":[3.543868508],"iteration":684,"passed_time":1.506604911,"remaining_time":0.6928183166},
{"learn":[3.542752124],"iteration":685,"passed_time":1.508126969,"remaining_time":0.6903088459},
{"learn":[3.541334315],"iteration":686,"passed_time":1.509394857,"remaining_time":0.6876864486},
{"learn":[3.540208266],"iteration":687,"passed_time":1.510694241,"remaining_time":0.6850822722},
{"learn":[3.537730983],"iteration":688,"passed_time":1.512039531,"remaining_time":0.6825026039},
{"learn":[3.53419867],"iteration":689,"passed_time":1.516207372,"remaining_time":0.6811946164},
{"learn":[3.532628335],"iteration":690,"passed_time":1.518182037,"remaining_time":0.6788976113},
{"learn":[3.532204987],"iteration":691,"passed_time":1.519578993,"remaining_time":0.6763444072},
{"learn":[3.530618147],"iteration":692,"passed_time":1.521074834,"remaining_time":0.6738383464},
{"learn":[3.528909306],"iteration":693,"passed_time":1.522515933,"remaining_time":0.6713110597},
{"learn":[3.526700678],"iteration":694,"passed_time":1.524071245,"remaining_time":0.6688370212},
{"learn":[3.526439574],"iteration":695,"passed_time":1.525488215,"remaining_time":0.6663051975},
{"learn":[3.525784216],"iteration":696,"passed_time":1.526964003,"remaining_time":0.6638021419},
{"learn":[3.524112693],"iteration":697,"passed_time":1.53007893,"remaining_time":0.6620112277},
{"learn":[3.522813541],"iteration":698,"passed_time":1.531412995,"remaining_time":0.6594496589},
{"learn":[3.519148203],"iteration":699,"passed_time":1.53376563,"remaining_time":0.657328127},
{"learn":[3.517236747],"iteration":700,"passed_time":1.536142235,"remaining_time":0.6552161599},
{"learn":[3.515603888],"iteration":701,"passed_time":1.537598532,"remaining_time":0.6527127672},
{"learn":[3.51263524],"iteration":702,"passed_time":1.53934131,"remaining_time":0.6503333843},
{"learn":[3.51123442],"iteration":703,"passed_time":1.541800577,"remaining_time":0.6482570609},
{"learn":[3.50828027],"iteration":704,"passed_time":1.544554865,"remaining_time":0.6463030997},
{"learn":[3.508265537],"iteration":705,"passed_time":1.545898433,"remaining_time":0.6437594042},
{"learn":[3.506774876],"iteration":706,"passed_time":1.547832312,"remaining_time":0.6414637444},
{"learn":[3.50552068],"iteration":707,"passed_time":1.549268478,"remaining_time":0.6389638357},
{"learn":[3.501973993],"iteration":708,"passed_time":1.550682038,"remaining_time":0.6364576487},
{"learn":[3.498880354],"iteration":709,"passed_time":1.553242973,"remaining_time":0.6344231862},
{"learn":[3.497370959],"iteration":710,"passed_time":1.554694147,"remaining_time":0.6319361581},
{"learn":[3.496050455],"iteration":711,"passed_time":1.556096942,"remaining_time":0.6294324709},
{"learn":[3.495630067],"iteration":712,"passed_time":1.557692036,"remaining_time":0.6270092768},
{"learn":[3.49550669],"iteration":713,"passed_time":1.559665273,"remaining_time":0.6247398713},
{"learn":[3.493652375],"iteration":714,"passed_time":1.561212275,"remaining_time":0.6223013961},
{"learn":[3.491915684],"iteration":715,"passed_time":1.563361397,"remaining_time":0.6201042412},
{"learn":[3.490303956],"iteration":716,"passed_time":1.56529016,"remaining_time":0.6178202446},
{"learn":[3.488363853],"iteration":717,"passed_time":1.566719877,"remaining_time":0.6153412332},
{"learn":[3.485483936],"iteration":718,"passed_time":1.568053546,"remaining_time":0.6128276029},
{"learn":[3.483763466],"iteration":719,"passed_time":1.569919993,"remaining_time":0.6105244418},
{"learn":[3.481642352],"iteration":720,"passed_time":1.573338693,"remaining_time":0.608823156},
{"learn":[3.479826119],"iteration":721,"passed_time":1.57517386,"remaining_time":0.6065073866},
{"learn":[3.478588728],"iteration":722,"passed_time":1.57660645,"remaining_time":0.6040387089},
{"learn":[3.475390887],"iteration":723,"passed_time":1.577973733,"remaining_time":0.6015479977},
{"learn":[3.472636852],"iteration":724,"passed_time":1.579249658,"remaining_time":0.5990257324},
{"learn":[3.47061883],"iteration":725,"passed_time":1.580520801,"remaining_time":0.5965050956},
{"learn":[3.46953149],"iteration":726,"passed_time":1.581760633,"remaining_time":0.5939761386},
{"learn":[3.467217162],"iteration":727,"passed_time":1.583083065,"remaining_time":0.5914815847},
{"learn":[3.465686216],"iteration":728,"passed_time":1.58440539,"remaining_time":0.5889902068},
{"learn":[3.462631216],"iteration":729,"passed_time":1.585740519,"remaining_time":0.5865067672},
{"learn":[3.461451053],"iteration":730,"passed_time":1.588771035,"remaining_time":0.5846503536},
{"learn":[3.458950469],"iteration":731,"passed_time":1.590365156,"remaining_time":0.5822648386},
{"learn":[3.458072145],"iteration":732,"passed_time":1.591952401,"remaining_time":0.5798789784},
{"learn":[3.454364268],"iteration":733,"passed_time":1.593288133,"remaining_time":0.5774041465},
{"learn":[3.453243406],"iteration":734,"passed_time":1.594562146,"remaining_time":0.5749101613},
{"learn":[3.453017963],"iteration":735,"passed_time":1.595767743,"remaining_time":0.5723949514},
{"learn":[3.45201581],"iteration":736,"passed_time":1.597019892,"remaining_time":0.5698999072},
{"learn":[3.449510107],"iteration":737,"passed_time":1.598503016,"remaining_time":0.5674902306},
{"learn":[3.447189189],"iteration":738,"passed_time":1.599797266,"remaining_time":0.5650163552},
{"learn":[3.446423605],"iteration":739,"passed_time":1.60151452,"remaining_time":0.562694291},
{"learn":[3.445531987],"iteration":740,"passed_time":1.602980983,"remaining_time":0.5602862007},
{"learn":[3.445328199],"iteration":741,"passed_time":1.604313829,"remaining_time":0.5578341885},
{"learn":[3.443327544],"iteration":742,"passed_time":1.605631264,"remaining_time":0.5553798583},
{"learn":[3.441475798],"iteration":743,"passed_time":1.606928256,"remaining_time":0.5529215505},
{"learn":[3.439046501],"iteration":744,"passed_time":1.608200287,"remaining_time":0.5504578162},
{"learn":[3.435899469],"iteration":745,"passed_time":1.609598204,"remaining_time":0.5480401391},
{"learn":[3.433988352],"iteration":746,"passed_time":1.611071249,"remaining_time":0.5456506371},
{"learn":[3.433413263],"iteration":747,"passed_time":1.612369376,"remaining_time":0.5432046561},
{"learn":[3.429944699],"iteration":748,"passed_time":1.613687164,"remaining_time":0.5407683287},
{"learn":[3.429291634],"iteration":749,"passed_time":1.614986464,"remaining_time":0.5383288212},
{"learn":[3.429175603],"iteration":750,"passed_time":1.616569811,"remaining_time":0.5359865286},
{"learn":[3.428780323],"iteration":751,"passed_time":1.617997363,"remaining_time":0.5335948751},
{"learn":[3.423893341],"iteration":752,"passed_time":1.619295814,"remaining_time":0.5311634343},
{"learn":[3.421024316],"iteration":753,"passed_time":1.620582078,"remaining_time":0.5287310229},
{"learn":[3.420969872],"iteration":754,"passed_time":1.621797279,"remaining_time":0.5262785873},
{"learn":[3.419544785],"iteration":755,"passed_time":1.623071655,"remaining_time":0.5238485237},
{"learn":[3.417057977],"iteration":756,"passed_time":1.624659023,"remaining_time":0.5215219849},
{"learn":[3.415160245],"iteration":757,"passed_time":1.626150164,"remaining_time":0.5191666749},
{"learn":[3.412854597],"iteration":758,"passed_time":1.628000273,"remaining_time":0.516927623},
{"learn":[3.410926347],"iteration":759,"passed_time":1.62952698,"remaining_time":0.5145874672},
{"learn":[3.408963843],"iteration":760,"passed_time":1.631662018,"remaining_time":0.5124405022},
{"learn":[3.407629634],"iteration":761,"passed_time":1.63308331,"remaining_time":0.5100706402},
{"learn":[3.404384724],"iteration":762,"passed_time":1.634471326,"remaining_time":0.5076929284},
{"learn":[3.403041656],"iteration":763,"passed_time":1.635863936,"remaining_time":0.5053192264},
{"learn":[3.401101731],"iteration":764,"passed_time":1.637373552,"remaining_time":0.5029840323},
{"learn":[3.400890668],"iteration":765,"passed_time":1.638725354,"remaining_time":0.5006027844},
{"learn":[3.399289941],"iteration":766,"passed_time":1.640015962,"remaining_time":0.4982056312},
{"learn":[3.399202366],"iteration":767,"passed_time":1.641436069,"remaining_time":0.4958504793},
{"learn":[3.397447845],"iteration":768,"passed_time":1.643402936,"remaining_time":0.4936620002},
{"learn":[3.394655341],"iteration":769,"passed_time":1.645428851,"remaining_time":0.4914917348},
{"learn":[3.393228229],"iteration":770,"passed_time":1.64735518,"remaining_time":0.4892922648},
{"learn":[3.389691197],"iteration":771,"passed_time":1.648901017,"remaining_time":0.4869811295},
{"learn":[3.389626772],"iteration":772,"passed_time":1.650436841,"remaining_time":0.4846690334},
{"learn":[3.388480222],"iteration":773,"passed_time":1.651867425,"remaining_time":0.4823282144},
{"learn":[3.388215066],"iteration":774,"passed_time":1.653141534,"remaining_time":0.4799443163},
{"learn":[3.386324358],"iteration":775,"passed_time":1.654518117,"remaining_time":0.4775928586},
{"learn":[3.383913061],"iteration":776,"passed_time":1.656007261,"remaining_time":0.4752762151},
{"learn":[3.382839768],"iteration":777,"passed_time":1.657274387,"remaining_time":0.4728983468},
{"learn":[3.381961844],"iteration":778,"passed_time":1.658563117,"remaining_time":0.4705294593},
{"learn":[3.381521703],"iteration":779,"passed_time":1.661337712,"remaining_time":0.4685824316},
{"learn":[3.380918963],"iteration":780,"passed_time":1.662744679,"remaining_time":0.4662497885},
{"learn":[3.377139006],"iteration":781,"passed_time":1.664089344,"remaining_time":0.4639021445},
{"learn":[3.376004372],"iteration":782,"passed_time":1.665374929,"remaining_time":0.4615406892},
{"learn":[3.373826468],"iteration":783,"passed_time":1.666631519,"remaining_time":0.45917399},
{"learn":[3.373546786],"iteration":784,"passed_time":1.667889987,"remaining_time":0.4568106334},
{"learn":[3.372109181],"iteration":785,"passed_time":1.669268751,"remaining_time":0.4544828405},
{"learn":[3.370764924],"iteration":786,"passed_time":1.6706115,"remaining_time":0.4521477123},
{"learn":[3.367833107],"iteration":787,"passed_time":1.671900746,"remaining_time":0.4498007082},
{"learn":[3.36450404],"iteration":788,"passed_time":1.674789351,"remaining_time":0.4478840977},
{"learn":[3.361794558],"iteration":789,"passed_time":1.676198865,"remaining_time":0.4455718503},
{"learn":[3.356880529],"iteration":790,"passed_time":1.677489851,"remaining_time":0.4432305675},
{"learn":[3.353843509],"iteration":791,"passed_time":1.678758109,"remaining_time":0.440885968},
{"learn":[3.353640253],"iteration":792,"passed_time":1.680000132,"remaining_time":0.4385372349},
{"learn":[3.353055088],"iteration":793,"passed_time":1.681210446,"remaining_time":0.4361830629},
{"learn":[3.351415617],"iteration":794,"passed_time":1.682477974,"remaining_time":0.4338465215},
{"learn":[3.349169061],"iteration":795,"passed_time":1.683748218,"remaining_time":0.4315133623},
{"learn":[3.346211014],"iteration":796,"passed_time":1.685073586,"remaining_time":0.4291969109},
{"learn":[3.344560452],"iteration":797,"passed_time":1.686327687,"remaining_time":0.4268649033},
{"learn":[3.344445461],"iteration":798,"passed_time":1.687542554,"remaining_time":0.4245257238},
{"learn":[3.342608898],"iteration":799,"passed_time":1.689346393,"remaining_time":0.4223365982},
{"learn":[3.339572899],"iteration":800,"passed_time":1.690691418,"remaining_time":0.4200344472},
{"learn":[3.339309302],"iteration":801,"passed_time":1.691994389,"remaining_time":0.4177243006},
{"learn":[3.33698088],"iteration":802,"passed_time":1.693336005,"remaining_time":0.4154261432},
{"learn":[3.334746342],"iteration":803,"passed_time":1.694751509,"remaining_time":0.4131483778},
{"learn":[3.332048511],"iteration":804,"passed_time":1.69602545,"remaining_time":0.410838463},
{"learn":[3.331932544],"iteration":805,"passed_time":1.697210321,"remaining_time":0.4085096803},
{"learn":[3.330541133],"iteration":806,"passed_time":1.698479757,"remaining_time":0.4062039568},
{"learn":[3.329124989],"iteration":807,"passed_time":1.699773461,"remaining_time":0.4039065649},
{"learn":[3.32583918],"iteration":808,"passed_time":1.701262329,"remaining_time":0.4016577316},
{"learn":[3.325287299],"iteration":809,"passed_time":1.70274529,"remaining_time":0.3994093889},
{"learn":[3.322745162],"iteration":810,"passed_time":1.70447729,"remaining_time":0.3972209713},
{"learn":[3.319733662],"iteration":811,"passed_time":1.70616058,"remaining_time":0.3950224003},
{"learn":[3.318080007],"iteration":812,"passed_time":1.707585059,"remaining_time":0.3927655671},
{"learn":[3.317179538],"iteration":813,"passed_time":1.70902161,"remaining_time":0.3905135374},
{"learn":[3.315685949],"iteration":814,"passed_time":1.710362136,"remaining_time":0.3882417118},
{"learn":[3.314944576],"iteration":815,"passed_time":1.711783997,"remaining_time":0.3859905091},
{"learn":[3.312369052],"iteration":816,"passed_time":1.713326232,"remaining_time":0.3837682992},
{"learn":[3.312321621],"iteration":817,"passed_time":1.714310284,"remaining_time":0.3814235596},
{"learn":[3.309465776],"iteration":818,"passed_time":1.715598547,"remaining_time":0.3791493736},
{"learn":[3.308307377],"iteration":819,"passed_time":1.71710669,"remaining_time":0.3769258587},
{"learn":[3.308076804],"iteration":820,"passed_time":1.718393218,"remaining_time":0.3746557686},
{"learn":[3.305643326],"iteration":821,"passed_time":1.719751099,"remaining_time":0.3724035226},
{"learn":[3.304154814],"iteration":822,"passed_time":1.721020813,"remaining_time":0.3701344883},
{"learn":[3.303076321],"iteration":823,"passed_time":1.722266122,"remaining_time":0.3678626668},
{"learn":[3.301746372],"iteration":824,"passed_time":1.723541401,"remaining_time":0.3655996911},
{"learn":[3.301345455],"iteration":825,"passed_time":1.724789024,"remaining_time":0.3633332811},
{"learn":[3.299181039],"iteration":826,"passed_time":1.726188256,"remaining_time":0.3611010498},
{"learn":[3.297989357],"iteration":827,"passed_time":1.727733602,"remaining_time":0.3589011831},
{"learn":[3.294775182],"iteration":828,"passed_time":1.729456474,"remaining_time":0.3567395139},
{"learn":[3.293840636],"iteration":829,"passed_time":1.731287913,"remaining_time":0.3546011388},
{"learn":[3.289279397],"iteration":830,"passed_time":1.733297511,"remaining_time":0.3524997345},
{"learn":[3.286204979],"iteration":831,"passed_time":1.734962516,"remaining_time":0.3503289695},
{"learn":[3.284833593],"iteration":832,"passed_time":1.736506078,"remaining_time":0.348135072},
{"learn":[3.283519914],"iteration":833,"passed_time":1.738065072,"remaining_time":0.3459458057},
{"learn":[3.282853026],"iteration":834,"passed_time":1.739848926,"remaining_time":0.3438024824},
{"learn":[3.281944673],"iteration":835,"passed_time":1.741806564,"remaining_time":0.3416941107},
{"learn":[3.279764865],"iteration":836,"passed_time":1.743420215,"remaining_time":0.33951911},
{"learn":[3.277468839],"iteration":837,"passed_time":1.745135035,"remaining_time":0.3373650068},
{"learn":[3.277124974],"iteration":838,"passed_time":1.747094696,"remaining_time":0.3352589344},
{"learn":[3.275636037],"iteration":839,"passed_time":1.748913003,"remaining_time":0.3331262863},
{"learn":[3.274413635],"iteration":840,"passed_time":1.750418517,"remaining_time":0.3309352487},
{"learn":[3.272636087],"iteration":841,"passed_time":1.751996691,"remaining_time":0.3287594742},
{"learn":[3.269644466],"iteration":842,"passed_time":1.753985922,"remaining_time":0.3266616722},
{"learn":[3.26852083],"iteration":843,"passed_time":1.755618712,"remaining_time":0.3244982453},
{"learn":[3.267820927],"iteration":844,"passed_time":1.757265184,"remaining_time":0.3223385841},
{"learn":[3.267331099],"iteration":845,"passed_time":1.759591343,"remaining_time":0.3203038615},
{"learn":[3.267231014],"iteration":846,"passed_time":1.762108032,"remaining_time":0.3183028676},
{"learn":[3.267158695],"iteration":847,"passed_time":1.764436002,"remaining_time":0.3162668306},
{"learn":[3.264718705],"iteration":848,"passed_time":1.766185043,"remaining_time":0.3141271396},
{"learn":[3.261678512],"iteration":849,"passed_time":1.767953119,"remaining_time":0.3119917269},
{"learn":[3.261368381],"iteration":850,"passed_time":1.769585376,"remaining_time":0.3098333972},
{"learn":[3.260128799],"iteration":851,"passed_time":1.771181004,"remaining_time":0.3076699396},
{"learn":[3.258972952],"iteration":852,"passed_time":1.772788933,"remaining_time":0.3055099334},
{"learn":[3.258724846],"iteration":853,"passed_time":1.774456657,"remaining_time":0.3033614425},
{"learn":[3.25686724],"iteration":854,"passed_time":1.776189041,"remaining_time":0.3012250421},
{"learn":[3.255750259],"iteration":855,"passed_time":1.777735704,"remaining_time":0.2990583427},
{"learn":[3.254915866],"iteration":856,"passed_time":1.779229582,"remaining_time":0.2968842827},
{"learn":[3.254348625],"iteration":857,"passed_time":1.780615063,"remaining_time":0.2946938683},
{"learn":[3.253408514],"iteration":858,"passed_time":1.782237215,"remaining_time":0.2925441761},
{"learn":[3.253291714],"iteration":859,"passed_time":1.783546549,"remaining_time":0.290344787},
{"learn":[3.250186342],"iteration":860,"passed_time":1.785001985,"remaining_time":0.2881710522},
{"learn":[3.249141318],"iteration":861,"passed_time":1.786340341,"remaining_time":0.2859802403},
{"learn":[3.246300388],"iteration":862,"passed_time":1.787724209,"remaining_time":0.2837986288},
{"learn":[3.245205135],"iteration":863,"passed_time":1.789116832,"remaining_time":0.281620242},
{"learn":[3.244403535],"iteration":864,"passed_time":1.791064796,"remaining_time":0.2795303438},
{"learn":[3.244211781],"iteration":865,"passed_time":1.792745994,"remaining_time":0.2773994957},
{"learn":[3.242286347],"iteration":866,"passed_time":1.794237566,"remaining_time":0.2752405954},
{"learn":[3.239606746],"iteration":867,"passed_time":1.795651496,"remaining_time":0.2730714256},
{"learn":[3.236773361],"iteration":868,"passed_time":1.797180782,"remaining_time":0.2709213837},
{"learn":[3.234552446],"iteration":869,"passed_time":1.800494474,"remaining_time":0.2690394041},
{"learn":[3.233724647],"iteration":870,"passed_time":1.80215191,"remaining_time":0.2669088362},
{"learn":[3.230851485],"iteration":871,"passed_time":1.803877232,"remaining_time":0.2647893185},
{"learn":[3.227728941],"iteration":872,"passed_time":1.805577182,"remaining_time":0.2626670127},
{"learn":[3.225787575],"iteration":873,"passed_time":1.807218181,"remaining_time":0.2605371749},
{"learn":[3.222797487],"iteration":874,"passed_time":1.808654015,"remaining_time":0.258379145},
{"learn":[3.22137014],"iteration":875,"passed_time":1.810434772,"remaining_time":0.2562715887},
{"learn":[3.219701963],"iteration":876,"passed_time":1.812022624,"remaining_time":0.2541377226},
{"learn":[3.21783327],"iteration":877,"passed_time":1.813592236,"remaining_time":0.2520025658},
{"learn":[3.217713355],"iteration":878,"passed_time":1.815001187,"remaining_time":0.2498465798},
{"learn":[3.217666091],"iteration":879,"passed_time":1.816593697,"remaining_time":0.2477173223},
{"learn":[3.214962005],"iteration":880,"passed_time":1.819065312,"remaining_time":0.2457080274},
{"learn":[3.214081828],"iteration":881,"passed_time":1.821319706,"remaining_time":0.2436686228},
{"learn":[3.213358337],"iteration":882,"passed_time":1.823396442,"remaining_time":0.2416051911},
{"learn":[3.210850401],"iteration":883,"passed_time":1.825252893,"remaining_time":0.2395128231},
{"learn":[3.207810328],"iteration":884,"passed_time":1.82682636,"remaining_time":0.2373842162},
{"learn":[3.204935073],"iteration":885,"passed_time":1.828485025,"remaining_time":0.2352678249},
{"learn":[3.20280198],"iteration":886,"passed_time":1.830111654,"remaining_time":0.2331483843},
{"learn":[3.200663495],"iteration":887,"passed_time":1.831971541,"remaining_time":0.2310594736},
{"learn":[3.197301669],"iteration":888,"passed_time":1.833533918,"remaining_time":0.2289339312},
{"learn":[3.195666943],"iteration":889,"passed_time":1.834962257,"remaining_time":0.2267930879},
{"learn":[3.193886506],"iteration":890,"passed_time":1.836743186,"remaining_time":0.2246969779},
{"learn":[3.190601248],"iteration":891,"passed_time":1.838182786,"remaining_time":0.2225602476},
{"learn":[3.188983797],"iteration":892,"passed_time":1.839770074,"remaining_time":0.2204427749},
{"learn":[3.187365749],"iteration":893,"passed_time":1.841468155,"remaining_time":0.2183396247},
{"learn":[3.186160771],"iteration":894,"passed_time":1.843024642,"remaining_time":0.2162207681},
{"learn":[3.185358981],"iteration":895,"passed_time":1.844571822,"remaining_time":0.2141020865},
{"learn":[3.183832164],"iteration":896,"passed_time":1.846140507,"remaining_time":0.2119871485},
{"learn":[3.183106966],"iteration":897,"passed_time":1.847617025,"remaining_time":0.2098629583},
{"learn":[3.182838152],"iteration":898,"passed_time":1.849108368,"remaining_time":0.2077418745},
{"learn":[3.180835453],"iteration":899,"passed_time":1.851040098,"remaining_time":0.205671122},
{"learn":[3.179957348],"iteration":900,"passed_time":1.852539423,"remaining_time":0.2035531663},
{"learn":[3.179752966],"iteration":901,"passed_time":1.853784843,"remaining_time":0.2014089962},
{"learn":[3.178851983],"iteration":902,"passed_time":1.855053292,"remaining_time":0.1992692905},
{"learn":[3.176748586],"iteration":903,"passed_time":1.856293043,"remaining_time":0.1971284647},
{"learn":[3.172960988],"iteration":904,"passed_time":1.857629244,"remaining_time":0.1949997549},
{"learn":[3.172794225],"iteration":905,"passed_time":1.858940478,"remaining_time":0.1928702041},
{"learn":[3.169996507],"iteration":906,"passed_time":1.860240234,"remaining_time":0.1907412809},
{"learn":[3.16813015],"iteration":907,"passed_time":1.8615582,"remaining_time":0.188616029},
{"learn":[3.166920871],"iteration":908,"passed_time":1.862828451,"remaining_time":0.1864877767},
{"learn":[3.16531606],"iteration":909,"passed_time":1.864097252,"remaining_time":0.1843612667},
{"learn":[3.162035247],"iteration":910,"passed_time":1.865708583,"remaining_time":0.1822701031},
{"learn":[3.16189467],"iteration":911,"passed_time":1.867947454,"remaining_time":0.1802405438},
{"learn":[3.161008416],"iteration":912,"passed_time":1.869268306,"remaining_time":0.1781230478},
{"learn":[3.160560787],"iteration":913,"passed_time":1.870560274,"remaining_time":0.1760045772},
{"learn":[3.160416261],"iteration":914,"passed_time":1.871964553,"remaining_time":0.1738983465},
{"learn":[3.15844291],"iteration":915,"passed_time":1.873272662,"remaining_time":0.1717848292},
{"learn":[3.155040501],"iteration":916,"passed_time":1.874568999,"remaining_time":0.1696720032},
{"learn":[3.154937548],"iteration":917,"passed_time":1.87589222,"remaining_time":0.1675633573},
{"learn":[3.153721161],"iteration":918,"passed_time":1.877185081,"remaining_time":0.1654537449},
{"learn":[3.153170511],"iteration":919,"passed_time":1.878524113,"remaining_time":0.1633499229},
{"learn":[3.153113601],"iteration":920,"passed_time":1.88023865,"remaining_time":0.161279971},
{"learn":[3.150607379],"iteration":921,"passed_time":1.881573842,"remaining_time":0.1591786981},
{"learn":[3.148408359],"iteration":922,"passed_time":1.882893524,"remaining_time":0.1570777913},
{"learn":[3.147495728],"iteration":923,"passed_time":1.884120789,"remaining_time":0.154970974},
{"learn":[3.146946235],"iteration":924,"passed_time":1.885404452,"remaining_time":0.1528706312},
{"learn":[3.14472738],"iteration":925,"passed_time":1.886687281,"remaining_time":0.1507719857},
{"learn":[3.144469477],"iteration":926,"passed_time":1.887902289,"remaining_time":0.1486697595},
{"learn":[3.142975516],"iteration":927,"passed_time":1.889159088,"remaining_time":0.1465726879},
{"learn":[3.14079113],"iteration":928,"passed_time":1.890410626,"remaining_time":0.1444770231},
{"learn":[3.138173032],"iteration":929,"passed_time":1.891772553,"remaining_time":0.1423914825},
{"learn":[3.136352813],"iteration":930,"passed_time":1.893158436,"remaining_time":0.1403092719},
{"learn":[3.133735004],"iteration":931,"passed_time":1.89460043,"remaining_time":0.1382326494},
{"learn":[3.1319496],"iteration":932,"passed_time":1.895971244,"remaining_time":0.1361522758},
{"learn":[3.129865343],"iteration":933,"passed_time":1.897329539,"remaining_time":0.134072537},
{"learn":[3.129830206],"iteration":934,"passed_time":1.898296716,"remaining_time":0.1319671514},
{"learn":[3.126676562],"iteration":935,"passed_time":1.89957855,"remaining_time":0.1298857128},
{"learn":[3.12645665],"iteration":936,"passed_time":1.900819344,"remaining_time":0.1278032217},
{"learn":[3.126378007],"iteration":937,"passed_time":1.902094374,"remaining_time":0.125724788},
{"learn":[3.124621914],"iteration":938,"passed_time":1.903384048,"remaining_time":0.123649017},
{"learn":[3.123379018],"iteration":939,"passed_time":1.904708658,"remaining_time":0.1215771484},
{"learn":[3.123332451],"iteration":940,"passed_time":1.90617201,"remaining_time":0.119515567},
{"learn":[3.122432444],"iteration":941,"passed_time":1.907526046,"remaining_time":0.1174485251},
{"learn":[3.121889006],"iteration":942,"passed_time":1.909084878,"remaining_time":0.1153953744},
{"learn":[3.121070914],"iteration":943,"passed_time":1.910585608,"remaining_time":0.1133398242},
{"learn":[3.118444705],"iteration":944,"passed_time":1.911884292,"remaining_time":0.111273689},
{"learn":[3.116820458],"iteration":945,"passed_time":1.91316313,"remaining_time":0.1092080434},
{"learn":[3.114971041],"iteration":946,"passed_time":1.91442828,"remaining_time":0.1071432934},
{"learn":[3.114685138],"iteration":947,"passed_time":1.915696895,"remaining_time":0.1050804204},
{"learn":[3.113399363],"iteration":948,"passed_time":1.916995332,"remaining_time":0.103020824},
{"learn":[3.110575399],"iteration":949,"passed_time":1.91833507,"remaining_time":0.1009650037},
{"learn":[3.110466553],"iteration":950,"passed_time":1.919610471,"remaining_time":0.09890737441},
{"learn":[3.108691641],"iteration":951,"passed_time":1.921678827,"remaining_time":0.09689136943},
{"learn":[3.107898017],"iteration":952,"passed_time":1.92298495,"remaining_time":0.09483766282},
{"learn":[3.105551729],"iteration":953,"passed_time":1.924705222,"remaining_time":0.0928054929},
{"learn":[3.104824945],"iteration":954,"passed_time":1.926148665,"remaining_time":0.09076093188},
{"learn":[3.103186704],"iteration":955,"passed_time":1.927524832,"remaining_time":0.08871453203},
{"learn":[3.102330655],"iteration":956,"passed_time":1.928829649,"remaining_time":0.08666632696},
{"learn":[3.102291298],"iteration":957,"passed_time":1.930141759,"remaining_time":0.08461999362},
{"learn":[3.100363529],"iteration":958,"passed_time":1.931420775,"remaining_time":0.08257377662},
{"learn":[3.097871596],"iteration":959,"passed_time":1.932712166,"remaining_time":0.08052967356},
{"learn":[3.097372213],"iteration":960,"passed_time":1.93398553,"remaining_time":0.0784864055},
{"learn":[3.095981813],"iteration":961,"passed_time":1.935239092,"remaining_time":0.07644395581},
{"learn":[3.095347452],"iteration":962,"passed_time":1.936790534,"remaining_time":0.07441458957},
{"learn":[3.094728409],"iteration":963,"passed_time":1.93981691,"remaining_time":0.07244129539},
{"learn":[3.094118537],"iteration":964,"passed_time":1.942217343,"remaining_time":0.07044311606},
{"learn":[3.093793695],"iteration":965,"passed_time":1.943905467,"remaining_time":0.06841903299},
{"learn":[3.092581602],"iteration":966,"passed_time":1.945271478,"remaining_time":0.0663846523},
{"learn":[3.091694202],"iteration":967,"passed_time":1.946613527,"remaining_time":0.06435086039},
{"learn":[3.090298312],"iteration":968,"passed_time":1.947905265,"remaining_time":0.0623168867},
{"learn":[3.090020107],"iteration":969,"passed_time":1.949168922,"remaining_time":0.06028357491},
{"learn":[3.088949869],"iteration":970,"passed_time":1.950540161,"remaining_time":0.05825506144},
{"learn":[3.086700204],"iteration":971,"passed_time":1.951814167,"remaining_time":0.05622509945},
{"learn":[3.086584317],"iteration":972,"passed_time":1.953298418,"remaining_time":0.05420252549},
{"learn":[3.084850742],"iteration":973,"passed_time":1.955362565,"remaining_time":0.05219653664},
{"learn":[3.084239948],"iteration":974,"passed_time":1.957117088,"remaining_time":0.05018248942},
{"learn":[3.082561673],"iteration":975,"passed_time":1.958395955,"remaining_time":0.04815727757},
{"learn":[3.07991814],"iteration":976,"passed_time":1.959668551,"remaining_time":0.04613344594},
{"learn":[3.079350277],"iteration":977,"passed_time":1.960907567,"remaining_time":0.04411039517},
{"learn":[3.077637462],"iteration":978,"passed_time":1.962186812,"remaining_time":0.04208980904},
{"learn":[3.076733301],"iteration":979,"passed_time":1.963590671,"remaining_time":0.04007327901},
{"learn":[3.07594065],"iteration":980,"passed_time":1.96491837,"remaining_time":0.03805652297},
{"learn":[3.072594655],"iteration":981,"passed_time":1.966242135,"remaining_time":0.0360410982},
{"learn":[3.071977674],"iteration":982,"passed_time":1.968587461,"remaining_time":0.03404474754},
{"learn":[3.069532634],"iteration":983,"passed_time":1.970221284,"remaining_time":0.03203611844},
{"learn":[3.068870784],"iteration":984,"passed_time":1.971465551,"remaining_time":0.03002231803},
{"learn":[3.068801463],"iteration":985,"passed_time":1.972670022,"remaining_time":0.0280095135},
{"learn":[3.067433249],"iteration":986,"passed_time":1.974006926,"remaining_time":0.02600009122},
{"learn":[3.065611456],"iteration":987,"passed_time":1.975262245,"remaining_time":0.02399103941},
{"learn":[3.063039162],"iteration":988,"passed_time":1.976631245,"remaining_time":0.02198477623},
{"learn":[3.06177873],"iteration":989,"passed_time":1.977900303,"remaining_time":0.01997879094},
{"learn":[3.061689148],"iteration":990,"passed_time":1.979163612,"remaining_time":0.01797424067},
{"learn":[3.058984039],"iteration":991,"passed_time":1.980420214,"remaining_time":0.01597113076},
{"learn":[3.057492984],"iteration":992,"passed_time":1.981679261,"remaining_time":0.01396954161},
{"learn":[3.057290731],"iteration":993,"passed_time":1.983670218,"remaining_time":0.0119738645},
{"learn":[3.056068348],"iteration":994,"passed_time":1.984920026,"remaining_time":0.00997447249},
{"learn":[3.054987307],"iteration":995,"passed_time":1.986207738,"remaining_time":0.007976737905},
{"learn":[3.054200234],"iteration":996,"passed_time":1.98750843,"remaining_time":0.005980466691},
{"learn":[3.052732869],"iteration":997,"passed_time":1.988796324,"remaining_time":0.003985563775},
{"learn":[3.051787862],"iteration":998,"passed_time":1.99014877,"remaining_time":0.001992140911},
{"learn":[3.051366222],"iteration":999,"passed_time":1.991407362,"remaining_time":0}
]}